{"version":3,"kind":"Article","sha256":"134d443c0618f90424f2753dea855949a0cbd5510ece40795705233ed2cd5251","slug":"auto","location":"/api/auto.md","dependencies":[],"frontmatter":{"title":"Auto-Generated API Documentation","content_includes_title":false,"authors":[{"nameParsed":{"literal":"Slide Forge Team","given":"Slide Forge","family":"Team"},"name":"Slide Forge Team","id":"contributors-myst-generated-uid-0"}],"github":"https://github.com/marvins/slide-forge","keywords":["latex","beamer","powerpoint","conversion","python"],"numbering":{"title":{"offset":1}},"source_url":"https://github.com/marvins/slide-forge/blob/main/docs/book/api/auto.md","edit_url":"https://github.com/marvins/slide-forge/edit/main/docs/book/api/auto.md","exports":[{"format":"md","filename":"auto.md","url":"/slide-forge/build/auto-a22600505274f783e37d5765923c96d2.md"}]},"mdast":{"type":"root","children":[{"type":"block","children":[{"type":"paragraph","position":{"start":{"line":3,"column":1},"end":{"line":3,"column":1}},"children":[{"type":"text","value":"This file is generated by ","position":{"start":{"line":3,"column":1},"end":{"line":3,"column":1}},"key":"i2Jjf9rqlP"},{"type":"inlineCode","value":"tools/generate_api_docs.py","position":{"start":{"line":3,"column":1},"end":{"line":3,"column":1}},"key":"NmRSl6FQcE"},{"type":"text","value":".","position":{"start":{"line":3,"column":1},"end":{"line":3,"column":1}},"key":"fW3nH8xys2"}],"key":"aKfoVHko3c"},{"type":"paragraph","position":{"start":{"line":5,"column":1},"end":{"line":5,"column":1}},"children":[{"type":"text","value":"Do not edit manually. Update docstrings in the source code instead.","position":{"start":{"line":5,"column":1},"end":{"line":5,"column":1}},"key":"T4RHay29xv"}],"key":"GA7n7kNSlZ"},{"type":"heading","depth":2,"position":{"start":{"line":7,"column":1},"end":{"line":7,"column":1}},"children":[{"type":"text","value":"Core","position":{"start":{"line":7,"column":1},"end":{"line":7,"column":1}},"key":"MaNrzKhfnE"}],"identifier":"core","label":"Core","html_id":"core","implicit":true,"key":"oJNsbSXCef"},{"type":"paragraph","position":{"start":{"line":9,"column":1},"end":{"line":9,"column":1}},"children":[{"type":"strong","position":{"start":{"line":9,"column":1},"end":{"line":9,"column":1}},"children":[{"type":"text","value":"Module:","position":{"start":{"line":9,"column":1},"end":{"line":9,"column":1}},"key":"ojLI7WoVn1"}],"key":"QFNNpVN3te"},{"type":"text","value":" ","position":{"start":{"line":9,"column":1},"end":{"line":9,"column":1}},"key":"r0IQGsEEaO"},{"type":"inlineCode","value":"slideforge.core","position":{"start":{"line":9,"column":1},"end":{"line":9,"column":1}},"key":"Vk8unyXkDo"}],"key":"XylPFMxVrQ"},{"type":"heading","depth":3,"position":{"start":{"line":11,"column":1},"end":{"line":11,"column":1}},"children":[{"type":"text","value":"Classes","position":{"start":{"line":11,"column":1},"end":{"line":11,"column":1}},"key":"GUWOWC3AFF"}],"identifier":"classes","label":"Classes","html_id":"classes","implicit":true,"key":"qoZndYl3Ai"},{"type":"heading","depth":4,"position":{"start":{"line":13,"column":1},"end":{"line":13,"column":1}},"children":[{"type":"inlineCode","value":"Slide_Forge","position":{"start":{"line":13,"column":1},"end":{"line":13,"column":1}},"key":"DC4M7hKwb0"}],"identifier":"slide-forge","label":"Slide_Forge","html_id":"slide-forge","implicit":true,"key":"CmEziHMdSd"},{"type":"paragraph","position":{"start":{"line":15,"column":1},"end":{"line":15,"column":1}},"children":[{"type":"inlineCode","value":"Slide_Forge()","position":{"start":{"line":15,"column":1},"end":{"line":15,"column":1}},"key":"Z7OXeFeQ27"}],"key":"ISIbdwdRfo"},{"type":"paragraph","position":{"start":{"line":17,"column":1},"end":{"line":17,"column":1}},"children":[{"type":"text","value":"Main controller for Slide Forge bidirectional conversions.","position":{"start":{"line":17,"column":1},"end":{"line":17,"column":1}},"key":"JJhrFWq2AI"}],"key":"df7hfKGQ26"},{"type":"paragraph","position":{"start":{"line":19,"column":1},"end":{"line":19,"column":1}},"children":[{"type":"text","value":"Supports conversions between LaTeX Beamer, PowerPoint, and other presentation formats.","position":{"start":{"line":19,"column":1},"end":{"line":19,"column":1}},"key":"Cs3n9vTFK9"}],"key":"Wm6MSXKJWN"},{"type":"paragraph","position":{"start":{"line":21,"column":1},"end":{"line":21,"column":1}},"children":[{"type":"strong","position":{"start":{"line":21,"column":1},"end":{"line":21,"column":1}},"children":[{"type":"text","value":"Methods","position":{"start":{"line":21,"column":1},"end":{"line":21,"column":1}},"key":"cmXZnHV5yh"}],"key":"MQh2K1POYo"}],"key":"Yiwf43RWZs"},{"type":"list","ordered":false,"spread":false,"position":{"start":{"line":23,"column":1},"end":{"line":31,"column":1}},"children":[{"type":"listItem","spread":true,"position":{"start":{"line":23,"column":1},"end":{"line":23,"column":1}},"children":[{"type":"paragraph","children":[{"type":"inlineCode","value":"convert_file(self, input_file: str, output_file: str, **kwargs) -> bool","position":{"start":{"line":23,"column":1},"end":{"line":23,"column":1}},"key":"QnDEdQFzAZ"}],"key":"n2G3SNVnWP"}],"key":"ZbcetxsAjy"},{"type":"listItem","spread":true,"position":{"start":{"line":24,"column":1},"end":{"line":24,"column":1}},"children":[{"type":"paragraph","children":[{"type":"inlineCode","value":"convert_string(self, content: str, output_file: str, source_format: str, **kwargs) -> bool","position":{"start":{"line":24,"column":1},"end":{"line":24,"column":1}},"key":"YxGb7RZYWS"}],"key":"vKcd1dLXO6"}],"key":"ZSApgmQMLF"},{"type":"listItem","spread":true,"position":{"start":{"line":25,"column":1},"end":{"line":25,"column":1}},"children":[{"type":"paragraph","children":[{"type":"inlineCode","value":"get_supported_conversions(self) -> List[tuple]","position":{"start":{"line":25,"column":1},"end":{"line":25,"column":1}},"key":"U9b6VTWIsV"}],"key":"NlMekuorsP"}],"key":"PoRNSLVKTW"},{"type":"listItem","spread":true,"position":{"start":{"line":26,"column":1},"end":{"line":26,"column":1}},"children":[{"type":"paragraph","children":[{"type":"inlineCode","value":"get_supported_formats(self) -> Dict[str, List[str]]","position":{"start":{"line":26,"column":1},"end":{"line":26,"column":1}},"key":"UpFPKRPx7p"}],"key":"YQAMgSDag8"}],"key":"LyWB83bT6j"},{"type":"listItem","spread":true,"position":{"start":{"line":27,"column":1},"end":{"line":27,"column":1}},"children":[{"type":"paragraph","children":[{"type":"inlineCode","value":"register_builder(self, format_name: str, builder: slideforge.base.Base_Builder)","position":{"start":{"line":27,"column":1},"end":{"line":27,"column":1}},"key":"wrX4egH2Wc"}],"key":"txqOxEvjek"}],"key":"aidVPLpVOm"},{"type":"listItem","spread":true,"position":{"start":{"line":28,"column":1},"end":{"line":28,"column":1}},"children":[{"type":"paragraph","children":[{"type":"inlineCode","value":"register_mapper(self, mapper: slideforge.base.Base_Mapper)","position":{"start":{"line":28,"column":1},"end":{"line":28,"column":1}},"key":"XXV7q118vJ"}],"key":"jMj9tkFVCU"}],"key":"SkcbUu8Uq2"},{"type":"listItem","spread":true,"position":{"start":{"line":29,"column":1},"end":{"line":29,"column":1}},"children":[{"type":"paragraph","children":[{"type":"inlineCode","value":"register_parser(self, format_name: str, parser: slideforge.base.Base_Parser)","position":{"start":{"line":29,"column":1},"end":{"line":29,"column":1}},"key":"XAY0zOKd2V"}],"key":"yS1rvKJ4Fx"}],"key":"vgCooh5dg1"},{"type":"listItem","spread":true,"position":{"start":{"line":30,"column":1},"end":{"line":31,"column":1}},"children":[{"type":"paragraph","children":[{"type":"inlineCode","value":"set_default_options(self, **kwargs)","position":{"start":{"line":30,"column":1},"end":{"line":30,"column":1}},"key":"DvhEYVH1qW"}],"key":"BN0HRmQTBA"}],"key":"fif3SsMrjx"}],"key":"JyqqQiRAFS"},{"type":"heading","depth":2,"position":{"start":{"line":32,"column":1},"end":{"line":32,"column":1}},"children":[{"type":"text","value":"Parsers","position":{"start":{"line":32,"column":1},"end":{"line":32,"column":1}},"key":"Uf9y6BJ2Kh"}],"identifier":"parsers","label":"Parsers","html_id":"parsers","implicit":true,"key":"fwvWxqfbIx"},{"type":"paragraph","position":{"start":{"line":34,"column":1},"end":{"line":34,"column":1}},"children":[{"type":"strong","position":{"start":{"line":34,"column":1},"end":{"line":34,"column":1}},"children":[{"type":"text","value":"Module:","position":{"start":{"line":34,"column":1},"end":{"line":34,"column":1}},"key":"FTgyhySV22"}],"key":"RfpergWMlg"},{"type":"text","value":" ","position":{"start":{"line":34,"column":1},"end":{"line":34,"column":1}},"key":"ugUv1TGykR"},{"type":"inlineCode","value":"slideforge.parsers.latex_parser","position":{"start":{"line":34,"column":1},"end":{"line":34,"column":1}},"key":"sz6lNIgLRF"}],"key":"zgFIAMHRaz"},{"type":"heading","depth":3,"position":{"start":{"line":36,"column":1},"end":{"line":36,"column":1}},"children":[{"type":"text","value":"Classes","position":{"start":{"line":36,"column":1},"end":{"line":36,"column":1}},"key":"NV7smVUbEo"}],"identifier":"classes","label":"Classes","html_id":"classes-1","implicit":true,"key":"sfUUv699ap"},{"type":"heading","depth":4,"position":{"start":{"line":38,"column":1},"end":{"line":38,"column":1}},"children":[{"type":"inlineCode","value":"LaTeX_Parser","position":{"start":{"line":38,"column":1},"end":{"line":38,"column":1}},"key":"PAr2tnzh0f"}],"identifier":"latex-parser","label":"LaTeX_Parser","html_id":"latex-parser","implicit":true,"key":"pjuilZGJGw"},{"type":"paragraph","position":{"start":{"line":40,"column":1},"end":{"line":40,"column":1}},"children":[{"type":"inlineCode","value":"LaTeX_Parser()","position":{"start":{"line":40,"column":1},"end":{"line":40,"column":1}},"key":"tOwa89Lq3s"}],"key":"h0TkKdFGT0"},{"type":"paragraph","position":{"start":{"line":42,"column":1},"end":{"line":42,"column":1}},"children":[{"type":"text","value":"Parser for LaTeX Beamer presentations.","position":{"start":{"line":42,"column":1},"end":{"line":42,"column":1}},"key":"slOl920iA1"}],"key":"qM2G6MYK8J"},{"type":"paragraph","position":{"start":{"line":44,"column":1},"end":{"line":44,"column":1}},"children":[{"type":"strong","position":{"start":{"line":44,"column":1},"end":{"line":44,"column":1}},"children":[{"type":"text","value":"Methods","position":{"start":{"line":44,"column":1},"end":{"line":44,"column":1}},"key":"K5xYTTTL9z"}],"key":"SbODsJ8MuU"}],"key":"onBKORPD5G"},{"type":"list","ordered":false,"spread":false,"position":{"start":{"line":46,"column":1},"end":{"line":50,"column":1}},"children":[{"type":"listItem","spread":true,"position":{"start":{"line":46,"column":1},"end":{"line":46,"column":1}},"children":[{"type":"paragraph","children":[{"type":"inlineCode","value":"get_supported_extensions(self) -> List[str]","position":{"start":{"line":46,"column":1},"end":{"line":46,"column":1}},"key":"Ahc6wyxEwn"}],"key":"NCYdjQMrGv"}],"key":"ZtOcfQNpaV"},{"type":"listItem","spread":true,"position":{"start":{"line":47,"column":1},"end":{"line":47,"column":1}},"children":[{"type":"paragraph","children":[{"type":"inlineCode","value":"parse_file(self, filepath: pathlib.Path, **kwargs) -> slideforge.models.universal.Universal_Document","position":{"start":{"line":47,"column":1},"end":{"line":47,"column":1}},"key":"jGUOqaVcat"}],"key":"RkeIhedlnH"}],"key":"cKNzHHVf6I"},{"type":"listItem","spread":true,"position":{"start":{"line":48,"column":1},"end":{"line":48,"column":1}},"children":[{"type":"paragraph","children":[{"type":"inlineCode","value":"parse_string(self, content: str, **kwargs) -> slideforge.models.universal.Universal_Document","position":{"start":{"line":48,"column":1},"end":{"line":48,"column":1}},"key":"YiUzAOHWIA"}],"key":"ZflTQsE1qW"}],"key":"BtxarOMvEd"},{"type":"listItem","spread":true,"position":{"start":{"line":49,"column":1},"end":{"line":50,"column":1}},"children":[{"type":"paragraph","children":[{"type":"inlineCode","value":"validate_file(self, filepath: pathlib.Path) -> bool","position":{"start":{"line":49,"column":1},"end":{"line":49,"column":1}},"key":"FMjW6iKFhE"}],"key":"CdgQeUUfD3"}],"key":"lQTjShbuAi"}],"key":"ctsSaint2A"},{"type":"heading","depth":2,"position":{"start":{"line":51,"column":1},"end":{"line":51,"column":1}},"children":[{"type":"text","value":"Mappers","position":{"start":{"line":51,"column":1},"end":{"line":51,"column":1}},"key":"mLa7ZEq215"}],"identifier":"mappers","label":"Mappers","html_id":"mappers","implicit":true,"key":"As5gDPzjSy"},{"type":"paragraph","position":{"start":{"line":53,"column":1},"end":{"line":53,"column":1}},"children":[{"type":"strong","position":{"start":{"line":53,"column":1},"end":{"line":53,"column":1}},"children":[{"type":"text","value":"Module:","position":{"start":{"line":53,"column":1},"end":{"line":53,"column":1}},"key":"yNbHY9Wsxa"}],"key":"kM7oihcexi"},{"type":"text","value":" ","position":{"start":{"line":53,"column":1},"end":{"line":53,"column":1}},"key":"EMTwMsX0Tn"},{"type":"inlineCode","value":"slideforge.mappers.content_mapper","position":{"start":{"line":53,"column":1},"end":{"line":53,"column":1}},"key":"iUBIoAyb7W"}],"key":"C2KzrzTdLU"},{"type":"heading","depth":3,"position":{"start":{"line":55,"column":1},"end":{"line":55,"column":1}},"children":[{"type":"text","value":"Classes","position":{"start":{"line":55,"column":1},"end":{"line":55,"column":1}},"key":"JtOXqwdfNg"}],"identifier":"classes","label":"Classes","html_id":"classes-2","implicit":true,"key":"RlkhbJsPc3"},{"type":"heading","depth":4,"position":{"start":{"line":57,"column":1},"end":{"line":57,"column":1}},"children":[{"type":"inlineCode","value":"Content_Mapper","position":{"start":{"line":57,"column":1},"end":{"line":57,"column":1}},"key":"phK2zbkeEc"}],"identifier":"content-mapper","label":"Content_Mapper","html_id":"content-mapper","implicit":true,"key":"KIsE1ihFh5"},{"type":"paragraph","position":{"start":{"line":59,"column":1},"end":{"line":59,"column":1}},"children":[{"type":"inlineCode","value":"Content_Mapper()","position":{"start":{"line":59,"column":1},"end":{"line":59,"column":1}},"key":"BvbBGY7BTA"}],"key":"qVnWOIQGGX"},{"type":"paragraph","position":{"start":{"line":61,"column":1},"end":{"line":61,"column":1}},"children":[{"type":"text","value":"Content mapper for bidirectional format conversions.","position":{"start":{"line":61,"column":1},"end":{"line":61,"column":1}},"key":"F9SJ3yQrzY"}],"key":"LgzVd6inGB"},{"type":"paragraph","position":{"start":{"line":63,"column":1},"end":{"line":63,"column":1}},"children":[{"type":"strong","position":{"start":{"line":63,"column":1},"end":{"line":63,"column":1}},"children":[{"type":"text","value":"Methods","position":{"start":{"line":63,"column":1},"end":{"line":63,"column":1}},"key":"GISH1CQ32b"}],"key":"jgHkPyKE2z"}],"key":"GJSbrVUtHp"},{"type":"list","ordered":false,"spread":false,"position":{"start":{"line":65,"column":1},"end":{"line":68,"column":1}},"children":[{"type":"listItem","spread":true,"position":{"start":{"line":65,"column":1},"end":{"line":65,"column":1}},"children":[{"type":"paragraph","children":[{"type":"inlineCode","value":"can_convert(self, source_format: str, target_format: str) -> bool","position":{"start":{"line":65,"column":1},"end":{"line":65,"column":1}},"key":"ScDTw5wL4r"}],"key":"PHIcoCmwBs"}],"key":"FW4P7HbIa7"},{"type":"listItem","spread":true,"position":{"start":{"line":66,"column":1},"end":{"line":66,"column":1}},"children":[{"type":"paragraph","children":[{"type":"inlineCode","value":"get_supported_conversions(self) -> Dict[str, List[str]]","position":{"start":{"line":66,"column":1},"end":{"line":66,"column":1}},"key":"IKyGWLJyls"}],"key":"hzkmNot89H"}],"key":"vC5YYPDmmK"},{"type":"listItem","spread":true,"position":{"start":{"line":67,"column":1},"end":{"line":68,"column":1}},"children":[{"type":"paragraph","children":[{"type":"inlineCode","value":"map_document(self, document: slideforge.models.universal.Universal_Document, target_format: str, **kwargs) -> List[Any]","position":{"start":{"line":67,"column":1},"end":{"line":67,"column":1}},"key":"Ak6vMCSXKX"}],"key":"nBhrJklKFO"}],"key":"IuoRkgX9jg"}],"key":"KpOZoDtdZ9"},{"type":"heading","depth":2,"position":{"start":{"line":69,"column":1},"end":{"line":69,"column":1}},"children":[{"type":"text","value":"Builders","position":{"start":{"line":69,"column":1},"end":{"line":69,"column":1}},"key":"cujEUCtI0G"}],"identifier":"builders","label":"Builders","html_id":"builders","implicit":true,"key":"qxmpzNnfeE"},{"type":"paragraph","position":{"start":{"line":71,"column":1},"end":{"line":71,"column":1}},"children":[{"type":"strong","position":{"start":{"line":71,"column":1},"end":{"line":71,"column":1}},"children":[{"type":"text","value":"Module:","position":{"start":{"line":71,"column":1},"end":{"line":71,"column":1}},"key":"cNwAfTLyGE"}],"key":"X1KSkCbFyX"},{"type":"text","value":" ","position":{"start":{"line":71,"column":1},"end":{"line":71,"column":1}},"key":"gpH7KknaxE"},{"type":"inlineCode","value":"slideforge.builders.powerpoint_builder","position":{"start":{"line":71,"column":1},"end":{"line":71,"column":1}},"key":"OpFu8CpyGH"}],"key":"LGRvjIvSAT"},{"type":"heading","depth":3,"position":{"start":{"line":73,"column":1},"end":{"line":73,"column":1}},"children":[{"type":"text","value":"Classes","position":{"start":{"line":73,"column":1},"end":{"line":73,"column":1}},"key":"CJB6ay7uMW"}],"identifier":"classes","label":"Classes","html_id":"classes-3","implicit":true,"key":"w3sx9Z0rhY"},{"type":"heading","depth":4,"position":{"start":{"line":75,"column":1},"end":{"line":75,"column":1}},"children":[{"type":"inlineCode","value":"PowerPoint_Builder","position":{"start":{"line":75,"column":1},"end":{"line":75,"column":1}},"key":"I543ZU5IbJ"}],"identifier":"powerpoint-builder","label":"PowerPoint_Builder","html_id":"powerpoint-builder","implicit":true,"key":"nIs2bgM9Ez"},{"type":"paragraph","position":{"start":{"line":77,"column":1},"end":{"line":77,"column":1}},"children":[{"type":"inlineCode","value":"PowerPoint_Builder()","position":{"start":{"line":77,"column":1},"end":{"line":77,"column":1}},"key":"zAlW2uhLZA"}],"key":"Cv3WGJXWvR"},{"type":"paragraph","position":{"start":{"line":79,"column":1},"end":{"line":79,"column":1}},"children":[{"type":"text","value":"Builder for PowerPoint presentations using python-pptx.","position":{"start":{"line":79,"column":1},"end":{"line":79,"column":1}},"key":"hzgdtvl0Fn"}],"key":"kJCVkUbXPE"},{"type":"paragraph","position":{"start":{"line":81,"column":1},"end":{"line":81,"column":1}},"children":[{"type":"strong","position":{"start":{"line":81,"column":1},"end":{"line":81,"column":1}},"children":[{"type":"text","value":"Methods","position":{"start":{"line":81,"column":1},"end":{"line":81,"column":1}},"key":"C9raRJ5XPB"}],"key":"hmJVpXolA9"}],"key":"awQyLkxKvH"},{"type":"list","ordered":false,"spread":false,"position":{"start":{"line":83,"column":1},"end":{"line":87,"column":1}},"children":[{"type":"listItem","spread":true,"position":{"start":{"line":83,"column":1},"end":{"line":83,"column":1}},"children":[{"type":"paragraph","children":[{"type":"inlineCode","value":"build_presentation(self, slides: List[slideforge.models.universal.Universal_Frame], output_file: pathlib.Path, **kwargs) -> bool","position":{"start":{"line":83,"column":1},"end":{"line":83,"column":1}},"key":"JlctOH3PwJ"}],"key":"EHxh3UKnry"}],"key":"PTJX8S4m6r"},{"type":"listItem","spread":true,"position":{"start":{"line":84,"column":1},"end":{"line":84,"column":1}},"children":[{"type":"paragraph","children":[{"type":"inlineCode","value":"get_default_theme(self) -> str","position":{"start":{"line":84,"column":1},"end":{"line":84,"column":1}},"key":"XIHtBhhNRS"}],"key":"eefV4wIsHF"}],"key":"UGibE9cWhz"},{"type":"listItem","spread":true,"position":{"start":{"line":85,"column":1},"end":{"line":85,"column":1}},"children":[{"type":"paragraph","children":[{"type":"inlineCode","value":"get_supported_extensions(self) -> List[str]","position":{"start":{"line":85,"column":1},"end":{"line":85,"column":1}},"key":"vEvCkSPxXo"}],"key":"WngQ3hYXnx"}],"key":"zbTRTMQaVP"},{"type":"listItem","spread":true,"position":{"start":{"line":86,"column":1},"end":{"line":87,"column":1}},"children":[{"type":"paragraph","children":[{"type":"inlineCode","value":"validate_output_path(self, output_file: pathlib.Path) -> bool","position":{"start":{"line":86,"column":1},"end":{"line":86,"column":1}},"key":"Hh5r1hZgky"}],"key":"R0BvnuzoW5"}],"key":"hOCS2G5hVu"}],"key":"FrrQpikdcb"},{"type":"heading","depth":2,"position":{"start":{"line":88,"column":1},"end":{"line":88,"column":1}},"children":[{"type":"text","value":"Models","position":{"start":{"line":88,"column":1},"end":{"line":88,"column":1}},"key":"tI8n5vkQak"}],"identifier":"models","label":"Models","html_id":"models","implicit":true,"key":"kh4NtPohAE"},{"type":"paragraph","position":{"start":{"line":90,"column":1},"end":{"line":90,"column":1}},"children":[{"type":"strong","position":{"start":{"line":90,"column":1},"end":{"line":90,"column":1}},"children":[{"type":"text","value":"Module:","position":{"start":{"line":90,"column":1},"end":{"line":90,"column":1}},"key":"luqbDuCtUg"}],"key":"zVblh0YqAJ"},{"type":"text","value":" ","position":{"start":{"line":90,"column":1},"end":{"line":90,"column":1}},"key":"ijRLZgEuFh"},{"type":"inlineCode","value":"slideforge.models.universal","position":{"start":{"line":90,"column":1},"end":{"line":90,"column":1}},"key":"mKRCMti0Nt"}],"key":"kJtbepdGib"},{"type":"heading","depth":3,"position":{"start":{"line":92,"column":1},"end":{"line":92,"column":1}},"children":[{"type":"text","value":"Classes","position":{"start":{"line":92,"column":1},"end":{"line":92,"column":1}},"key":"ZlKD3ZhQcn"}],"identifier":"classes","label":"Classes","html_id":"classes-4","implicit":true,"key":"UpP37bXa5d"},{"type":"heading","depth":4,"position":{"start":{"line":94,"column":1},"end":{"line":94,"column":1}},"children":[{"type":"inlineCode","value":"Conversion_Options","position":{"start":{"line":94,"column":1},"end":{"line":94,"column":1}},"key":"B8Fhah3duL"}],"identifier":"conversion-options","label":"Conversion_Options","html_id":"conversion-options","implicit":true,"key":"F8kEzaAgDy"},{"type":"paragraph","position":{"start":{"line":96,"column":1},"end":{"line":96,"column":1}},"children":[{"type":"inlineCode","value":"Conversion_Options(theme: str = 'default', preserve_colors: bool = True, preserve_fonts: bool = True, preserve_layouts: bool = True, include_images: bool = True, include_notes: bool = False, verbose: bool = False, output_format: Optional[str] = None, custom_settings: Dict[str, Any] = <factory>) -> None","position":{"start":{"line":96,"column":1},"end":{"line":96,"column":1}},"key":"UehkrdeRWC"}],"key":"vbl0V1hQZF"},{"type":"paragraph","position":{"start":{"line":98,"column":1},"end":{"line":98,"column":1}},"children":[{"type":"text","value":"Options for conversion processes.","position":{"start":{"line":98,"column":1},"end":{"line":98,"column":1}},"key":"Bxp3AfvlNx"}],"key":"iRIVQGaVwu"},{"type":"paragraph","position":{"start":{"line":100,"column":1},"end":{"line":100,"column":1}},"children":[{"type":"strong","position":{"start":{"line":100,"column":1},"end":{"line":100,"column":1}},"children":[{"type":"text","value":"Methods","position":{"start":{"line":100,"column":1},"end":{"line":100,"column":1}},"key":"AkA5T88zax"}],"key":"Xklomk41ba"}],"key":"WnZPqV3VXA"},{"type":"list","ordered":false,"spread":false,"position":{"start":{"line":102,"column":1},"end":{"line":103,"column":1}},"children":[{"type":"listItem","spread":true,"position":{"start":{"line":102,"column":1},"end":{"line":103,"column":1}},"children":[{"type":"paragraph","children":[{"type":"inlineCode","value":"to_dict(self) -> Dict[str, Any]","position":{"start":{"line":102,"column":1},"end":{"line":102,"column":1}},"key":"QG9LTYcx1y"}],"key":"NKJteybvYa"}],"key":"KrALm4EWcp"}],"key":"tUWwehU82J"},{"type":"heading","depth":4,"position":{"start":{"line":104,"column":1},"end":{"line":104,"column":1}},"children":[{"type":"inlineCode","value":"Element_Type","position":{"start":{"line":104,"column":1},"end":{"line":104,"column":1}},"key":"I1nH8a2yWA"}],"identifier":"element-type","label":"Element_Type","html_id":"element-type","implicit":true,"key":"SolXBaC4ZT"},{"type":"paragraph","position":{"start":{"line":106,"column":1},"end":{"line":106,"column":1}},"children":[{"type":"inlineCode","value":"Element_Type(value, names=None, *, module=None, qualname=None, type=None, start=1, boundary=None)","position":{"start":{"line":106,"column":1},"end":{"line":106,"column":1}},"key":"gIesh3vx4w"}],"key":"QtR6P3Xhli"},{"type":"paragraph","position":{"start":{"line":108,"column":1},"end":{"line":108,"column":1}},"children":[{"type":"text","value":"Universal element types that exist across formats.","position":{"start":{"line":108,"column":1},"end":{"line":108,"column":1}},"key":"lICIXq9NKg"}],"key":"Jro8CUtOgg"},{"type":"heading","depth":4,"position":{"start":{"line":110,"column":1},"end":{"line":110,"column":1}},"children":[{"type":"inlineCode","value":"Formatting","position":{"start":{"line":110,"column":1},"end":{"line":110,"column":1}},"key":"pOGVpeCAEJ"}],"identifier":"formatting","label":"Formatting","html_id":"formatting","implicit":true,"key":"OZ10eotm5D"},{"type":"paragraph","position":{"start":{"line":112,"column":1},"end":{"line":112,"column":1}},"children":[{"type":"inlineCode","value":"Formatting(value, names=None, *, module=None, qualname=None, type=None, start=1, boundary=None)","position":{"start":{"line":112,"column":1},"end":{"line":112,"column":1}},"key":"ZulGqD1DPg"}],"key":"VM34eVkMNh"},{"type":"paragraph","position":{"start":{"line":114,"column":1},"end":{"line":114,"column":1}},"children":[{"type":"text","value":"Text formatting options.","position":{"start":{"line":114,"column":1},"end":{"line":114,"column":1}},"key":"CAvRzpl3ap"}],"key":"riYUHIfBuD"},{"type":"heading","depth":4,"position":{"start":{"line":116,"column":1},"end":{"line":116,"column":1}},"children":[{"type":"inlineCode","value":"Layout_Type","position":{"start":{"line":116,"column":1},"end":{"line":116,"column":1}},"key":"PSfTQl1JgT"}],"identifier":"layout-type","label":"Layout_Type","html_id":"layout-type","implicit":true,"key":"MGYmkVNnA7"},{"type":"paragraph","position":{"start":{"line":118,"column":1},"end":{"line":118,"column":1}},"children":[{"type":"inlineCode","value":"Layout_Type(value, names=None, *, module=None, qualname=None, type=None, start=1, boundary=None)","position":{"start":{"line":118,"column":1},"end":{"line":118,"column":1}},"key":"bin98np3cJ"}],"key":"oql1rdl9B5"},{"type":"paragraph","position":{"start":{"line":120,"column":1},"end":{"line":120,"column":1}},"children":[{"type":"text","value":"Universal slide layout types.","position":{"start":{"line":120,"column":1},"end":{"line":120,"column":1}},"key":"xq9mf8LKVZ"}],"key":"wD7Nr8Eid8"},{"type":"heading","depth":4,"position":{"start":{"line":122,"column":1},"end":{"line":122,"column":1}},"children":[{"type":"inlineCode","value":"Metadata","position":{"start":{"line":122,"column":1},"end":{"line":122,"column":1}},"key":"aEgmdfekuk"}],"identifier":"metadata","label":"Metadata","html_id":"metadata","implicit":true,"key":"zXjeuW1Zrj"},{"type":"paragraph","position":{"start":{"line":124,"column":1},"end":{"line":124,"column":1}},"children":[{"type":"inlineCode","value":"Metadata(title: Optional[str] = None, author: Optional[str] = None, date: Optional[str] = None, institution: Optional[str] = None, subject: Optional[str] = None, keywords: List[str] = <factory>, language: Optional[str] = None, version: Optional[str] = None, created_date: Optional[str] = None, modified_date: Optional[str] = None, custom_properties: Dict[str, Any] = <factory>) -> None","position":{"start":{"line":124,"column":1},"end":{"line":124,"column":1}},"key":"kzbsYw6NXM"}],"key":"zqw1yTB0Hl"},{"type":"paragraph","position":{"start":{"line":126,"column":1},"end":{"line":126,"column":1}},"children":[{"type":"text","value":"Universal metadata for presentations.","position":{"start":{"line":126,"column":1},"end":{"line":126,"column":1}},"key":"vuQEkumMvg"}],"key":"w2ZIxUoL5r"},{"type":"heading","depth":4,"position":{"start":{"line":128,"column":1},"end":{"line":128,"column":1}},"children":[{"type":"inlineCode","value":"Position","position":{"start":{"line":128,"column":1},"end":{"line":128,"column":1}},"key":"PIHkUByKTS"}],"identifier":"position","label":"Position","html_id":"position","implicit":true,"key":"RrFu1AYpSk"},{"type":"paragraph","position":{"start":{"line":130,"column":1},"end":{"line":130,"column":1}},"children":[{"type":"inlineCode","value":"Position(x: float, y: float, width: Optional[float] = None, height: Optional[float] = None) -> None","position":{"start":{"line":130,"column":1},"end":{"line":130,"column":1}},"key":"T4h9UDTRvT"}],"key":"NhHtWUeb5d"},{"type":"paragraph","position":{"start":{"line":132,"column":1},"end":{"line":132,"column":1}},"children":[{"type":"text","value":"Position information for elements.","position":{"start":{"line":132,"column":1},"end":{"line":132,"column":1}},"key":"lmgB8nSkOI"}],"key":"E5HXC5Y5uB"},{"type":"heading","depth":4,"position":{"start":{"line":134,"column":1},"end":{"line":134,"column":1}},"children":[{"type":"inlineCode","value":"Size","position":{"start":{"line":134,"column":1},"end":{"line":134,"column":1}},"key":"YZ9g7435p8"}],"identifier":"size","label":"Size","html_id":"size","implicit":true,"key":"lQOxbGA6aM"},{"type":"paragraph","position":{"start":{"line":136,"column":1},"end":{"line":136,"column":1}},"children":[{"type":"inlineCode","value":"Size(width: float, height: float, scale: Optional[float] = None) -> None","position":{"start":{"line":136,"column":1},"end":{"line":136,"column":1}},"key":"pjS4PEEp25"}],"key":"ImMNCNqQDw"},{"type":"paragraph","position":{"start":{"line":138,"column":1},"end":{"line":138,"column":1}},"children":[{"type":"text","value":"Size information for elements.","position":{"start":{"line":138,"column":1},"end":{"line":138,"column":1}},"key":"QeCk2LAP9T"}],"key":"W4p4cW4Jeg"},{"type":"heading","depth":4,"position":{"start":{"line":140,"column":1},"end":{"line":140,"column":1}},"children":[{"type":"inlineCode","value":"Text_Content","position":{"start":{"line":140,"column":1},"end":{"line":140,"column":1}},"key":"ObGAQD9q74"}],"identifier":"text-content","label":"Text_Content","html_id":"text-content","implicit":true,"key":"zaA9NTAXJN"},{"type":"paragraph","position":{"start":{"line":142,"column":1},"end":{"line":142,"column":1}},"children":[{"type":"inlineCode","value":"Text_Content(text: str, formatting: List[slideforge.models.universal.Formatting] = <factory>, font_size: Optional[str] = None, font_color: Optional[str] = None, font_family: Optional[str] = None) -> None","position":{"start":{"line":142,"column":1},"end":{"line":142,"column":1}},"key":"zjoDhiaBK5"}],"key":"yuhE21f2wp"},{"type":"paragraph","position":{"start":{"line":144,"column":1},"end":{"line":144,"column":1}},"children":[{"type":"text","value":"Text content with formatting information.","position":{"start":{"line":144,"column":1},"end":{"line":144,"column":1}},"key":"xFJ4Q37WoL"}],"key":"NzMNvu982X"},{"type":"heading","depth":4,"position":{"start":{"line":146,"column":1},"end":{"line":146,"column":1}},"children":[{"type":"inlineCode","value":"Universal_Document","position":{"start":{"line":146,"column":1},"end":{"line":146,"column":1}},"key":"J37PrXIA6A"}],"identifier":"universal-document","label":"Universal_Document","html_id":"universal-document","implicit":true,"key":"dnd0LE6wbo"},{"type":"paragraph","position":{"start":{"line":148,"column":1},"end":{"line":148,"column":1}},"children":[{"type":"inlineCode","value":"Universal_Document(metadata: slideforge.models.universal.Metadata = <factory>, frames: List[slideforge.models.universal.Universal_Frame] = <factory>, source_format: Optional[str] = None, source_path: Optional[pathlib.Path] = None, global_settings: Dict[str, Any] = <factory>) -> None","position":{"start":{"line":148,"column":1},"end":{"line":148,"column":1}},"key":"oOev1hRIgI"}],"key":"L3KompSWi5"},{"type":"paragraph","position":{"start":{"line":150,"column":1},"end":{"line":150,"column":1}},"children":[{"type":"text","value":"Universal document representation - format-agnostic.","position":{"start":{"line":150,"column":1},"end":{"line":150,"column":1}},"key":"z9XznoywgW"}],"key":"rmuzF924xq"},{"type":"paragraph","position":{"start":{"line":152,"column":1},"end":{"line":152,"column":1}},"children":[{"type":"strong","position":{"start":{"line":152,"column":1},"end":{"line":152,"column":1}},"children":[{"type":"text","value":"Methods","position":{"start":{"line":152,"column":1},"end":{"line":152,"column":1}},"key":"nY3D6fcC8q"}],"key":"I10G3kDYrr"}],"key":"hTlnhnxJSz"},{"type":"list","ordered":false,"spread":false,"position":{"start":{"line":154,"column":1},"end":{"line":158,"column":1}},"children":[{"type":"listItem","spread":true,"position":{"start":{"line":154,"column":1},"end":{"line":154,"column":1}},"children":[{"type":"paragraph","children":[{"type":"inlineCode","value":"add_frame(self, frame: slideforge.models.universal.Universal_Frame) -> None","position":{"start":{"line":154,"column":1},"end":{"line":154,"column":1}},"key":"o7y64Wgic6"}],"key":"hPlmE3HzWL"}],"key":"oJoIUBWDao"},{"type":"listItem","spread":true,"position":{"start":{"line":155,"column":1},"end":{"line":155,"column":1}},"children":[{"type":"paragraph","children":[{"type":"inlineCode","value":"get_frame_by_number(self, frame_number: int) -> Optional[slideforge.models.universal.Universal_Frame]","position":{"start":{"line":155,"column":1},"end":{"line":155,"column":1}},"key":"sVAkmYxnrc"}],"key":"aBdxSUSYj1"}],"key":"B92emdAx1c"},{"type":"listItem","spread":true,"position":{"start":{"line":156,"column":1},"end":{"line":156,"column":1}},"children":[{"type":"paragraph","children":[{"type":"inlineCode","value":"get_title_frame(self) -> Optional[slideforge.models.universal.Universal_Frame]","position":{"start":{"line":156,"column":1},"end":{"line":156,"column":1}},"key":"nGoPw7v2Dd"}],"key":"dUT2rXgsMp"}],"key":"D5mLs5JlRC"},{"type":"listItem","spread":true,"position":{"start":{"line":157,"column":1},"end":{"line":158,"column":1}},"children":[{"type":"paragraph","children":[{"type":"inlineCode","value":"get_total_frames(self) -> int","position":{"start":{"line":157,"column":1},"end":{"line":157,"column":1}},"key":"ttaxX2XDUC"}],"key":"jDBPIfnA9F"}],"key":"TGC8b58E65"}],"key":"Q3zP18jhKT"},{"type":"heading","depth":4,"position":{"start":{"line":159,"column":1},"end":{"line":159,"column":1}},"children":[{"type":"inlineCode","value":"Universal_Element","position":{"start":{"line":159,"column":1},"end":{"line":159,"column":1}},"key":"f2fvkA3PAw"}],"identifier":"universal-element","label":"Universal_Element","html_id":"universal-element","implicit":true,"key":"oVV3dBuC7r"},{"type":"paragraph","position":{"start":{"line":161,"column":1},"end":{"line":161,"column":1}},"children":[{"type":"inlineCode","value":"Universal_Element(element_type: slideforge.models.universal.Element_Type, content: Union[str, slideforge.models.universal.Text_Content, Dict[str, Any]], position: Optional[slideforge.models.universal.Position] = None, size: Optional[slideforge.models.universal.Size] = None, level: int = 0, style: Dict[str, Any] = <factory>, metadata: Dict[str, Any] = <factory>) -> None","position":{"start":{"line":161,"column":1},"end":{"line":161,"column":1}},"key":"PQQhBPgTiu"}],"key":"AmLqZxtphN"},{"type":"paragraph","position":{"start":{"line":163,"column":1},"end":{"line":163,"column":1}},"children":[{"type":"text","value":"Universal element that can represent content from any format.","position":{"start":{"line":163,"column":1},"end":{"line":163,"column":1}},"key":"nmBujwL3HA"}],"key":"xhcnwChjDK"},{"type":"paragraph","position":{"start":{"line":165,"column":1},"end":{"line":165,"column":1}},"children":[{"type":"strong","position":{"start":{"line":165,"column":1},"end":{"line":165,"column":1}},"children":[{"type":"text","value":"Methods","position":{"start":{"line":165,"column":1},"end":{"line":165,"column":1}},"key":"SrAMDRlckV"}],"key":"hyI9sNqsXQ"}],"key":"gkPnOAQk6a"},{"type":"list","ordered":false,"spread":false,"position":{"start":{"line":167,"column":1},"end":{"line":168,"column":1}},"children":[{"type":"listItem","spread":true,"position":{"start":{"line":167,"column":1},"end":{"line":168,"column":1}},"children":[{"type":"paragraph","children":[{"type":"inlineCode","value":"to_text_content(self) -> Optional[slideforge.models.universal.Text_Content]","position":{"start":{"line":167,"column":1},"end":{"line":167,"column":1}},"key":"NMWrjWp8ln"}],"key":"FkqU9j3Ulp"}],"key":"gBBazbyOIL"}],"key":"o4q1FgF04L"},{"type":"heading","depth":4,"position":{"start":{"line":169,"column":1},"end":{"line":169,"column":1}},"children":[{"type":"inlineCode","value":"Universal_Frame","position":{"start":{"line":169,"column":1},"end":{"line":169,"column":1}},"key":"gRjm5hWm5L"}],"identifier":"universal-frame","label":"Universal_Frame","html_id":"universal-frame","implicit":true,"key":"z86hY98Sqq"},{"type":"paragraph","position":{"start":{"line":171,"column":1},"end":{"line":171,"column":1}},"children":[{"type":"inlineCode","value":"Universal_Frame(frame_number: int, title: Optional[str] = None, subtitle: Optional[str] = None, elements: List[slideforge.models.universal.Universal_Element] = <factory>, layout: slideforge.models.universal.Layout_Type = <Layout_Type.TITLE_AND_CONTENT: 'title_and_content'>, background_color: Optional[str] = None, notes: Optional[str] = None, metadata: Dict[str, Any] = <factory>) -> None","position":{"start":{"line":171,"column":1},"end":{"line":171,"column":1}},"key":"V2fOmQzTSa"}],"key":"GUc11hOSXE"},{"type":"paragraph","position":{"start":{"line":173,"column":1},"end":{"line":173,"column":1}},"children":[{"type":"text","value":"Universal frame/slide representation.","position":{"start":{"line":173,"column":1},"end":{"line":173,"column":1}},"key":"VsoaLESspX"}],"key":"lPfCHDtmk9"},{"type":"paragraph","position":{"start":{"line":175,"column":1},"end":{"line":175,"column":1}},"children":[{"type":"strong","position":{"start":{"line":175,"column":1},"end":{"line":175,"column":1}},"children":[{"type":"text","value":"Methods","position":{"start":{"line":175,"column":1},"end":{"line":175,"column":1}},"key":"v6BUmuXw3K"}],"key":"BXX6HPqE68"}],"key":"ty2CVFWYgs"},{"type":"list","ordered":false,"spread":false,"position":{"start":{"line":177,"column":1},"end":{"line":180,"column":1}},"children":[{"type":"listItem","spread":true,"position":{"start":{"line":177,"column":1},"end":{"line":177,"column":1}},"children":[{"type":"paragraph","children":[{"type":"inlineCode","value":"add_element(self, element: slideforge.models.universal.Universal_Element) -> None","position":{"start":{"line":177,"column":1},"end":{"line":177,"column":1}},"key":"qXBbsTZDsM"}],"key":"PpKd3xBDcS"}],"key":"MC9YK9enyP"},{"type":"listItem","spread":true,"position":{"start":{"line":178,"column":1},"end":{"line":178,"column":1}},"children":[{"type":"paragraph","children":[{"type":"inlineCode","value":"get_elements_by_type(self, element_type: slideforge.models.universal.Element_Type) -> List[slideforge.models.universal.Universal_Element]","position":{"start":{"line":178,"column":1},"end":{"line":178,"column":1}},"key":"jWGIIjQW0r"}],"key":"f2T6Gr8Glu"}],"key":"QQFRXpMqqj"},{"type":"listItem","spread":true,"position":{"start":{"line":179,"column":1},"end":{"line":180,"column":1}},"children":[{"type":"paragraph","children":[{"type":"inlineCode","value":"get_text_elements(self) -> List[slideforge.models.universal.Universal_Element]","position":{"start":{"line":179,"column":1},"end":{"line":179,"column":1}},"key":"S3JNMp0AV3"}],"key":"UCEEKUx4iV"}],"key":"btzDt3bVjO"}],"key":"NLGYDhwn9u"},{"type":"heading","depth":3,"position":{"start":{"line":181,"column":1},"end":{"line":181,"column":1}},"children":[{"type":"text","value":"Functions","position":{"start":{"line":181,"column":1},"end":{"line":181,"column":1}},"key":"BCZxRtOJr7"}],"identifier":"functions","label":"Functions","html_id":"functions","implicit":true,"key":"WxXdPM4yUx"},{"type":"heading","depth":4,"position":{"start":{"line":183,"column":1},"end":{"line":183,"column":1}},"children":[{"type":"inlineCode","value":"create_equation_element","position":{"start":{"line":183,"column":1},"end":{"line":183,"column":1}},"key":"XyY35nGvJ6"}],"identifier":"create-equation-element","label":"create_equation_element","html_id":"create-equation-element","implicit":true,"key":"eqDOAHIZ4J"},{"type":"paragraph","position":{"start":{"line":185,"column":1},"end":{"line":185,"column":1}},"children":[{"type":"inlineCode","value":"create_equation_element(latex: str, equation_type: str = 'inline') -> slideforge.models.universal.Universal_Element","position":{"start":{"line":185,"column":1},"end":{"line":185,"column":1}},"key":"jcwfESVKDu"}],"key":"l3Je6vTTVu"},{"type":"paragraph","position":{"start":{"line":187,"column":1},"end":{"line":187,"column":1}},"children":[{"type":"text","value":"Create an equation element with LaTeX content.","position":{"start":{"line":187,"column":1},"end":{"line":187,"column":1}},"key":"v8Ia7gU1WV"}],"key":"P1jOLhd7Y3"},{"type":"heading","depth":4,"position":{"start":{"line":189,"column":1},"end":{"line":189,"column":1}},"children":[{"type":"inlineCode","value":"create_image_element","position":{"start":{"line":189,"column":1},"end":{"line":189,"column":1}},"key":"gZhDefvrDf"}],"identifier":"create-image-element","label":"create_image_element","html_id":"create-image-element","implicit":true,"key":"jZaGJCApxn"},{"type":"paragraph","position":{"start":{"line":191,"column":1},"end":{"line":191,"column":1}},"children":[{"type":"inlineCode","value":"create_image_element(image_path: str, caption: str = None, position: slideforge.models.universal.Position = None, size: slideforge.models.universal.Size = None) -> slideforge.models.universal.Universal_Element","position":{"start":{"line":191,"column":1},"end":{"line":191,"column":1}},"key":"wLP6aQG7tn"}],"key":"k0UxvjhMCZ"},{"type":"paragraph","position":{"start":{"line":193,"column":1},"end":{"line":193,"column":1}},"children":[{"type":"text","value":"Create an image element.","position":{"start":{"line":193,"column":1},"end":{"line":193,"column":1}},"key":"lE23q66CRw"}],"key":"Mm57u2lJoZ"},{"type":"heading","depth":4,"position":{"start":{"line":195,"column":1},"end":{"line":195,"column":1}},"children":[{"type":"inlineCode","value":"create_itemize_element","position":{"start":{"line":195,"column":1},"end":{"line":195,"column":1}},"key":"O3C9f13xvC"}],"identifier":"create-itemize-element","label":"create_itemize_element","html_id":"create-itemize-element","implicit":true,"key":"eShOPUY6rp"},{"type":"paragraph","position":{"start":{"line":197,"column":1},"end":{"line":197,"column":1}},"children":[{"type":"inlineCode","value":"create_itemize_element(items: List[str], level: int = 0) -> slideforge.models.universal.Universal_Element","position":{"start":{"line":197,"column":1},"end":{"line":197,"column":1}},"key":"Cy1dh1tDym"}],"key":"cOD3d0sQCf"},{"type":"paragraph","position":{"start":{"line":199,"column":1},"end":{"line":199,"column":1}},"children":[{"type":"text","value":"Create an itemize (bullet list) element.","position":{"start":{"line":199,"column":1},"end":{"line":199,"column":1}},"key":"xj5PTemQ25"}],"key":"WgaqAZSqSY"},{"type":"heading","depth":4,"position":{"start":{"line":201,"column":1},"end":{"line":201,"column":1}},"children":[{"type":"inlineCode","value":"create_text_element","position":{"start":{"line":201,"column":1},"end":{"line":201,"column":1}},"key":"Yvuiuu8JfX"}],"identifier":"create-text-element","label":"create_text_element","html_id":"create-text-element","implicit":true,"key":"JxnT0vGV1h"},{"type":"paragraph","position":{"start":{"line":203,"column":1},"end":{"line":203,"column":1}},"children":[{"type":"inlineCode","value":"create_text_element(text: str, element_type: slideforge.models.universal.Element_Type = <Element_Type.TEXT: 'text'>, formatting: List[slideforge.models.universal.Formatting] = None) -> slideforge.models.universal.Universal_Element","position":{"start":{"line":203,"column":1},"end":{"line":203,"column":1}},"key":"yCAASuRKQx"}],"key":"oS95C3Iu4d"},{"type":"paragraph","position":{"start":{"line":205,"column":1},"end":{"line":205,"column":1}},"children":[{"type":"text","value":"Create a text element with optional formatting.","position":{"start":{"line":205,"column":1},"end":{"line":205,"column":1}},"key":"Mt5d3dCvzw"}],"key":"U3JzGvK1aN"},{"type":"heading","depth":4,"position":{"start":{"line":207,"column":1},"end":{"line":207,"column":1}},"children":[{"type":"inlineCode","value":"merge_documents","position":{"start":{"line":207,"column":1},"end":{"line":207,"column":1}},"key":"DJIzUyLpiM"}],"identifier":"merge-documents","label":"merge_documents","html_id":"merge-documents","implicit":true,"key":"sXtVf2TYAX"},{"type":"paragraph","position":{"start":{"line":209,"column":1},"end":{"line":209,"column":1}},"children":[{"type":"inlineCode","value":"merge_documents(doc1: slideforge.models.universal.Universal_Document, doc2: slideforge.models.universal.Universal_Document) -> slideforge.models.universal.Universal_Document","position":{"start":{"line":209,"column":1},"end":{"line":209,"column":1}},"key":"hXC3uCH4mC"}],"key":"cFeX6YZzvE"},{"type":"paragraph","position":{"start":{"line":211,"column":1},"end":{"line":211,"column":1}},"children":[{"type":"text","value":"Merge two universal documents.","position":{"start":{"line":211,"column":1},"end":{"line":211,"column":1}},"key":"GFfXMdnKGY"}],"key":"eOsbUIbOzN"},{"type":"heading","depth":2,"position":{"start":{"line":213,"column":1},"end":{"line":213,"column":1}},"children":[{"type":"text","value":"Exceptions","position":{"start":{"line":213,"column":1},"end":{"line":213,"column":1}},"key":"W5MvSBKpU8"}],"identifier":"exceptions","label":"Exceptions","html_id":"exceptions","implicit":true,"key":"AL8lMuIteK"},{"type":"paragraph","position":{"start":{"line":215,"column":1},"end":{"line":215,"column":1}},"children":[{"type":"strong","position":{"start":{"line":215,"column":1},"end":{"line":215,"column":1}},"children":[{"type":"text","value":"Module:","position":{"start":{"line":215,"column":1},"end":{"line":215,"column":1}},"key":"VNu7Ts4px9"}],"key":"Kmauey7UFb"},{"type":"text","value":" ","position":{"start":{"line":215,"column":1},"end":{"line":215,"column":1}},"key":"O3RsZkaCYu"},{"type":"inlineCode","value":"slideforge.exceptions","position":{"start":{"line":215,"column":1},"end":{"line":215,"column":1}},"key":"vJvkYWx1tg"}],"key":"oPgzCW5TD3"},{"type":"heading","depth":3,"position":{"start":{"line":217,"column":1},"end":{"line":217,"column":1}},"children":[{"type":"text","value":"Classes","position":{"start":{"line":217,"column":1},"end":{"line":217,"column":1}},"key":"HMLEmlFm4q"}],"identifier":"classes","label":"Classes","html_id":"classes-5","implicit":true,"key":"EEtDkSHCjg"},{"type":"heading","depth":4,"position":{"start":{"line":219,"column":1},"end":{"line":219,"column":1}},"children":[{"type":"inlineCode","value":"BuilderError","position":{"start":{"line":219,"column":1},"end":{"line":219,"column":1}},"key":"Ij5pMs1JaY"}],"identifier":"buildererror","label":"BuilderError","html_id":"buildererror","implicit":true,"key":"ADK8SS7gJk"},{"type":"paragraph","position":{"start":{"line":221,"column":1},"end":{"line":221,"column":1}},"children":[{"type":"inlineCode","value":"BuilderError(message: str, slide_number: int = None, operation: str = None, output_format: str = None)","position":{"start":{"line":221,"column":1},"end":{"line":221,"column":1}},"key":"SyIBFLrJfm"}],"key":"tE5y1J7YJc"},{"type":"paragraph","position":{"start":{"line":223,"column":1},"end":{"line":223,"column":1}},"children":[{"type":"text","value":"Error raised during building of output files.","position":{"start":{"line":223,"column":1},"end":{"line":223,"column":1}},"key":"LQqTFy7nSu"}],"key":"g7lQ3hbAdf"},{"type":"heading","depth":4,"position":{"start":{"line":225,"column":1},"end":{"line":225,"column":1}},"children":[{"type":"inlineCode","value":"ConfigurationError","position":{"start":{"line":225,"column":1},"end":{"line":225,"column":1}},"key":"KVNvdEQMfT"}],"identifier":"configurationerror","label":"ConfigurationError","html_id":"configurationerror","implicit":true,"key":"P6w6AEjDa5"},{"type":"paragraph","position":{"start":{"line":227,"column":1},"end":{"line":227,"column":1}},"children":[{"type":"inlineCode","value":"ConfigurationError(message: str, config_key: str = None, config_value: str = None)","position":{"start":{"line":227,"column":1},"end":{"line":227,"column":1}},"key":"zIKItYkqMM"}],"key":"PcuLqIMupJ"},{"type":"paragraph","position":{"start":{"line":229,"column":1},"end":{"line":229,"column":1}},"children":[{"type":"text","value":"Error raised due to configuration issues.","position":{"start":{"line":229,"column":1},"end":{"line":229,"column":1}},"key":"MuTQbczJhl"}],"key":"cIjdtbPhCQ"},{"type":"heading","depth":4,"position":{"start":{"line":231,"column":1},"end":{"line":231,"column":1}},"children":[{"type":"inlineCode","value":"ConversionError","position":{"start":{"line":231,"column":1},"end":{"line":231,"column":1}},"key":"JPKpPAFyjM"}],"identifier":"conversionerror","label":"ConversionError","html_id":"conversionerror","implicit":true,"key":"XzHqnK50Xe"},{"type":"paragraph","position":{"start":{"line":233,"column":1},"end":{"line":233,"column":1}},"children":[{"type":"inlineCode","value":"ConversionError(message: str, source_file: str = None, target_file: str = None, stage: str = None)","position":{"start":{"line":233,"column":1},"end":{"line":233,"column":1}},"key":"ast4IfPFsE"}],"key":"K1MJTCYRiB"},{"type":"paragraph","position":{"start":{"line":235,"column":1},"end":{"line":235,"column":1}},"children":[{"type":"text","value":"Error raised during the conversion process.","position":{"start":{"line":235,"column":1},"end":{"line":235,"column":1}},"key":"PrguqELNxa"}],"key":"KVmQM8fXe4"},{"type":"heading","depth":4,"position":{"start":{"line":237,"column":1},"end":{"line":237,"column":1}},"children":[{"type":"inlineCode","value":"MappingError","position":{"start":{"line":237,"column":1},"end":{"line":237,"column":1}},"key":"AXMMg94Ih4"}],"identifier":"mappingerror","label":"MappingError","html_id":"mappingerror","implicit":true,"key":"N8B0BwiAlI"},{"type":"paragraph","position":{"start":{"line":239,"column":1},"end":{"line":239,"column":1}},"children":[{"type":"inlineCode","value":"MappingError(message: str, element_type: str = None, source_format: str = None, target_format: str = None)","position":{"start":{"line":239,"column":1},"end":{"line":239,"column":1}},"key":"tNlGtpGRbe"}],"key":"Uh0sFvtaSU"},{"type":"paragraph","position":{"start":{"line":241,"column":1},"end":{"line":241,"column":1}},"children":[{"type":"text","value":"Error raised during content mapping between formats.","position":{"start":{"line":241,"column":1},"end":{"line":241,"column":1}},"key":"mKAgyaHUJZ"}],"key":"VprRqe7MUV"},{"type":"heading","depth":4,"position":{"start":{"line":243,"column":1},"end":{"line":243,"column":1}},"children":[{"type":"inlineCode","value":"ParseError","position":{"start":{"line":243,"column":1},"end":{"line":243,"column":1}},"key":"jXYAPWgfgD"}],"identifier":"parseerror","label":"ParseError","html_id":"parseerror","implicit":true,"key":"Y2vjsawP5t"},{"type":"paragraph","position":{"start":{"line":245,"column":1},"end":{"line":245,"column":1}},"children":[{"type":"inlineCode","value":"ParseError(message: str, line_number: int = None, file_path: str = None, latex_snippet: str = None)","position":{"start":{"line":245,"column":1},"end":{"line":245,"column":1}},"key":"Tqrs43blIW"}],"key":"oJDb8CLCse"},{"type":"paragraph","position":{"start":{"line":247,"column":1},"end":{"line":247,"column":1}},"children":[{"type":"text","value":"Error raised during parsing of input files.","position":{"start":{"line":247,"column":1},"end":{"line":247,"column":1}},"key":"BgwYo1eAeD"}],"key":"oD1Xt2Ixu9"},{"type":"heading","depth":4,"position":{"start":{"line":249,"column":1},"end":{"line":249,"column":1}},"children":[{"type":"inlineCode","value":"Slide_Forge_Error","position":{"start":{"line":249,"column":1},"end":{"line":249,"column":1}},"key":"zJaIAG9p41"}],"identifier":"slide-forge-error","label":"Slide_Forge_Error","html_id":"slide-forge-error","implicit":true,"key":"MV6U1c7QcO"},{"type":"paragraph","position":{"start":{"line":251,"column":1},"end":{"line":251,"column":1}},"children":[{"type":"inlineCode","value":"Slide_Forge_Error(message: str, details: dict = None)","position":{"start":{"line":251,"column":1},"end":{"line":251,"column":1}},"key":"erFET0N1rw"}],"key":"Uv4yrTOdGJ"},{"type":"paragraph","position":{"start":{"line":253,"column":1},"end":{"line":253,"column":1}},"children":[{"type":"text","value":"Base exception for all Slide Forge errors.","position":{"start":{"line":253,"column":1},"end":{"line":253,"column":1}},"key":"PPJlJqqRvp"}],"key":"v3OgUlfUrQ"},{"type":"heading","depth":4,"position":{"start":{"line":255,"column":1},"end":{"line":255,"column":1}},"children":[{"type":"inlineCode","value":"UnsupportedFormatError","position":{"start":{"line":255,"column":1},"end":{"line":255,"column":1}},"key":"P5MTtZ3Rjo"}],"identifier":"unsupportedformaterror","label":"UnsupportedFormatError","html_id":"unsupportedformaterror","implicit":true,"key":"PDbjLsyhMr"},{"type":"paragraph","position":{"start":{"line":257,"column":1},"end":{"line":257,"column":1}},"children":[{"type":"inlineCode","value":"UnsupportedFormatError(message: str, format_name: str = None, operation: str = None)","position":{"start":{"line":257,"column":1},"end":{"line":257,"column":1}},"key":"kA4G4JdlJw"}],"key":"YKZc0niX1l"},{"type":"paragraph","position":{"start":{"line":259,"column":1},"end":{"line":259,"column":1}},"children":[{"type":"text","value":"Error raised when trying to use an unsupported format.","position":{"start":{"line":259,"column":1},"end":{"line":259,"column":1}},"key":"BODRroLbTQ"}],"key":"cJ5U0vS52f"},{"type":"heading","depth":4,"position":{"start":{"line":261,"column":1},"end":{"line":261,"column":1}},"children":[{"type":"inlineCode","value":"ValidationError","position":{"start":{"line":261,"column":1},"end":{"line":261,"column":1}},"key":"HMVWCzHRa7"}],"identifier":"validationerror","label":"ValidationError","html_id":"validationerror","implicit":true,"key":"TFXtAszkx0"},{"type":"paragraph","position":{"start":{"line":263,"column":1},"end":{"line":263,"column":1}},"children":[{"type":"inlineCode","value":"ValidationError(message: str, field: str = None, value: str = None)","position":{"start":{"line":263,"column":1},"end":{"line":263,"column":1}},"key":"QmUfSLfVbo"}],"key":"WGVlYVM89L"},{"type":"paragraph","position":{"start":{"line":265,"column":1},"end":{"line":265,"column":1}},"children":[{"type":"text","value":"Error raised during validation of inputs or outputs.","position":{"start":{"line":265,"column":1},"end":{"line":265,"column":1}},"key":"y3pcV6hWAH"}],"key":"BKKK2FQKSg"},{"type":"heading","depth":2,"position":{"start":{"line":267,"column":1},"end":{"line":267,"column":1}},"children":[{"type":"text","value":"CLI","position":{"start":{"line":267,"column":1},"end":{"line":267,"column":1}},"key":"GbGSZ8cKpu"}],"identifier":"cli","label":"CLI","html_id":"cli","implicit":true,"key":"Vw3Me8HuJt"},{"type":"paragraph","position":{"start":{"line":269,"column":1},"end":{"line":269,"column":1}},"children":[{"type":"strong","position":{"start":{"line":269,"column":1},"end":{"line":269,"column":1}},"children":[{"type":"text","value":"Module:","position":{"start":{"line":269,"column":1},"end":{"line":269,"column":1}},"key":"OtdYLWeWik"}],"key":"SmOp5rkJBi"},{"type":"text","value":" ","position":{"start":{"line":269,"column":1},"end":{"line":269,"column":1}},"key":"NRUqyW4Hd5"},{"type":"inlineCode","value":"slideforge.apps.cli","position":{"start":{"line":269,"column":1},"end":{"line":269,"column":1}},"key":"hwnk7JvPM1"}],"key":"OMFSmizAf8"},{"type":"heading","depth":3,"position":{"start":{"line":271,"column":1},"end":{"line":271,"column":1}},"children":[{"type":"text","value":"Functions","position":{"start":{"line":271,"column":1},"end":{"line":271,"column":1}},"key":"wUMPvAIdKn"}],"identifier":"functions","label":"Functions","html_id":"functions-1","implicit":true,"key":"fv3bbuoSAS"},{"type":"heading","depth":4,"position":{"start":{"line":273,"column":1},"end":{"line":273,"column":1}},"children":[{"type":"inlineCode","value":"convert_file","position":{"start":{"line":273,"column":1},"end":{"line":273,"column":1}},"key":"LXHqB60Zt8"}],"identifier":"convert-file","label":"convert_file","html_id":"convert-file","implicit":true,"key":"GloFibCDYn"},{"type":"paragraph","position":{"start":{"line":275,"column":1},"end":{"line":275,"column":1}},"children":[{"type":"inlineCode","value":"convert_file(args: argparse.Namespace) -> int","position":{"start":{"line":275,"column":1},"end":{"line":275,"column":1}},"key":"XZy2gSMllR"}],"key":"hHM3qR4ibu"},{"type":"paragraph","position":{"start":{"line":277,"column":1},"end":{"line":277,"column":1}},"children":[{"type":"text","value":"Perform the conversion with given arguments","position":{"start":{"line":277,"column":1},"end":{"line":277,"column":1}},"key":"rTwTwoXnHN"}],"key":"Vwgk5cVoaQ"},{"type":"heading","depth":4,"position":{"start":{"line":279,"column":1},"end":{"line":279,"column":1}},"children":[{"type":"inlineCode","value":"create_parser","position":{"start":{"line":279,"column":1},"end":{"line":279,"column":1}},"key":"NJospVhLje"}],"identifier":"create-parser","label":"create_parser","html_id":"create-parser","implicit":true,"key":"CXcBHCI0x1"},{"type":"paragraph","position":{"start":{"line":281,"column":1},"end":{"line":281,"column":1}},"children":[{"type":"inlineCode","value":"create_parser() -> argparse.ArgumentParser","position":{"start":{"line":281,"column":1},"end":{"line":281,"column":1}},"key":"Y0RKI5e2Zt"}],"key":"XCqqXmiYpN"},{"type":"paragraph","position":{"start":{"line":283,"column":1},"end":{"line":283,"column":1}},"children":[{"type":"text","value":"Create command-line argument parser","position":{"start":{"line":283,"column":1},"end":{"line":283,"column":1}},"key":"tfgwlM7YbT"}],"key":"B23Ger5oEC"},{"type":"heading","depth":4,"position":{"start":{"line":285,"column":1},"end":{"line":285,"column":1}},"children":[{"type":"inlineCode","value":"main","position":{"start":{"line":285,"column":1},"end":{"line":285,"column":1}},"key":"KrLjneC1tt"}],"identifier":"main","label":"main","html_id":"main","implicit":true,"key":"kWcxRDCFDU"},{"type":"paragraph","position":{"start":{"line":287,"column":1},"end":{"line":287,"column":1}},"children":[{"type":"inlineCode","value":"main() -> int","position":{"start":{"line":287,"column":1},"end":{"line":287,"column":1}},"key":"xkjHi8janp"}],"key":"Z8i18OTnQe"},{"type":"paragraph","position":{"start":{"line":289,"column":1},"end":{"line":289,"column":1}},"children":[{"type":"text","value":"Main CLI entry point","position":{"start":{"line":289,"column":1},"end":{"line":289,"column":1}},"key":"IfMaKLV2xE"}],"key":"gezx2SYu05"},{"type":"heading","depth":4,"position":{"start":{"line":291,"column":1},"end":{"line":291,"column":1}},"children":[{"type":"inlineCode","value":"validate_inputs","position":{"start":{"line":291,"column":1},"end":{"line":291,"column":1}},"key":"eX9ChWdvHI"}],"identifier":"validate-inputs","label":"validate_inputs","html_id":"validate-inputs","implicit":true,"key":"vCSbuzgURQ"},{"type":"paragraph","position":{"start":{"line":293,"column":1},"end":{"line":293,"column":1}},"children":[{"type":"inlineCode","value":"validate_inputs(input_file: str, output_file: str) -> bool","position":{"start":{"line":293,"column":1},"end":{"line":293,"column":1}},"key":"zjUdREOu3J"}],"key":"qPCaMYGsud"},{"type":"paragraph","position":{"start":{"line":295,"column":1},"end":{"line":295,"column":1}},"children":[{"type":"text","value":"Validate input and output file paths","position":{"start":{"line":295,"column":1},"end":{"line":295,"column":1}},"key":"qlyMoCb5rj"}],"key":"R04FQXTYRF"}],"key":"CaIYEAfHnn"}],"key":"pUFnVaBI5Q"},"references":{"cite":{"order":[],"data":{}}},"footer":{"navigation":{"prev":{"title":"Quick Start","url":"/quickstart","group":"Getting Started"},"next":{"title":"Class Diagrams","url":"/class-diagrams","group":"Reference"}}},"domain":"http://localhost:3000"}