{"version":3,"kind":"Article","sha256":"084cb42601c39f7c08e961ec1bd7659caf591848867b78e71ed5953878b7421a","slug":"design-notes","location":"/design-notes.md","dependencies":[],"frontmatter":{"title":"Design Notes","content_includes_title":false,"authors":[{"nameParsed":{"literal":"Slide Forge Team","given":"Slide Forge","family":"Team"},"name":"Slide Forge Team","id":"contributors-myst-generated-uid-0"}],"github":"https://github.com/marvins/slide-forge","keywords":["latex","beamer","powerpoint","conversion","python"],"numbering":{"title":{"offset":1}},"source_url":"https://github.com/marvins/slide-forge/blob/main/docs/book/design-notes.md","edit_url":"https://github.com/marvins/slide-forge/edit/main/docs/book/design-notes.md","exports":[{"format":"md","filename":"design-notes.md","url":"/slide-forge//build/design-notes-eedf00a017fb7cfa050e9c88558c5d43.md"}]},"mdast":{"type":"root","children":[{"type":"block","children":[{"type":"paragraph","position":{"start":{"line":3,"column":1},"end":{"line":3,"column":1}},"children":[{"type":"text","value":"This page contains the original design documentation and architectural decisions for Slide Forge, along with insights from implementation.","position":{"start":{"line":3,"column":1},"end":{"line":3,"column":1}},"key":"qFjVPkMmJM"}],"key":"msh6h1AnjW"},{"type":"heading","depth":2,"position":{"start":{"line":5,"column":1},"end":{"line":5,"column":1}},"children":[{"type":"text","value":"Overview","position":{"start":{"line":5,"column":1},"end":{"line":5,"column":1}},"key":"XkvezbobaD"}],"identifier":"overview","label":"Overview","html_id":"overview","implicit":true,"key":"JrtypV8y1y"},{"type":"paragraph","position":{"start":{"line":7,"column":1},"end":{"line":7,"column":1}},"children":[{"type":"text","value":"Slide Forge is a Python library for creating PowerPoint presentations. It is a wrapper around the python-pptx library, and provides a simple interface for creating presentations.","position":{"start":{"line":7,"column":1},"end":{"line":7,"column":1}},"key":"E8unjUaZu2"}],"key":"JlipDGHKG2"},{"type":"heading","depth":2,"position":{"start":{"line":9,"column":1},"end":{"line":9,"column":1}},"children":[{"type":"text","value":"Design Decisions","position":{"start":{"line":9,"column":1},"end":{"line":9,"column":1}},"key":"R5wvBuoQ1d"}],"identifier":"design-decisions","label":"Design Decisions","html_id":"design-decisions","implicit":true,"key":"r39wkE3fB6"},{"type":"list","ordered":true,"start":1,"spread":false,"position":{"start":{"line":11,"column":1},"end":{"line":13,"column":1}},"children":[{"type":"listItem","spread":true,"position":{"start":{"line":11,"column":1},"end":{"line":11,"column":1}},"children":[{"type":"paragraph","children":[{"type":"text","value":"Use python-pptx for PowerPoint creation","position":{"start":{"line":11,"column":1},"end":{"line":11,"column":1}},"key":"G7qcEsCpuc"}],"key":"bNaKnnq8PW"}],"key":"l8kq77Wcut"},{"type":"listItem","spread":true,"position":{"start":{"line":12,"column":1},"end":{"line":13,"column":1}},"children":[{"type":"paragraph","children":[{"type":"text","value":"Input is a Tex file, with Beamer class.","position":{"start":{"line":12,"column":1},"end":{"line":12,"column":1}},"key":"OQr9TTZsIS"}],"key":"vZuBqbemlT"}],"key":"kMEglupd4O"}],"key":"NaWh4Y1TeX"},{"type":"heading","depth":2,"position":{"start":{"line":14,"column":1},"end":{"line":14,"column":1}},"children":[{"type":"text","value":"Questions for Cascade","position":{"start":{"line":14,"column":1},"end":{"line":14,"column":1}},"key":"wPJt5Kt8fx"}],"identifier":"questions-for-cascade","label":"Questions for Cascade","html_id":"questions-for-cascade","implicit":true,"key":"yGqWra519A"},{"type":"list","ordered":true,"start":1,"spread":false,"position":{"start":{"line":16,"column":1},"end":{"line":19,"column":1}},"children":[{"type":"listItem","spread":true,"position":{"start":{"line":16,"column":1},"end":{"line":16,"column":1}},"children":[{"type":"paragraph","children":[{"type":"text","value":"What’s the best workflow for LaTeX → PowerPoint conversion?","position":{"start":{"line":16,"column":1},"end":{"line":16,"column":1}},"key":"f3LiOJencs"}],"key":"LBNtVuLwLZ"}],"key":"UrkM0svrOR"},{"type":"listItem","spread":true,"position":{"start":{"line":17,"column":1},"end":{"line":17,"column":1}},"children":[{"type":"paragraph","children":[{"type":"text","value":"Should we use AST-like parsing or template-based approach?","position":{"start":{"line":17,"column":1},"end":{"line":17,"column":1}},"key":"hhSA81NVnP"}],"key":"yKI5SO0Fag"}],"key":"JrzX2RragO"},{"type":"listItem","spread":true,"position":{"start":{"line":18,"column":1},"end":{"line":19,"column":1}},"children":[{"type":"paragraph","children":[{"type":"text","value":"How do we handle complex LaTeX structures?","position":{"start":{"line":18,"column":1},"end":{"line":18,"column":1}},"key":"vYu4y50BYr"}],"key":"Xk8KmTfVU9"}],"key":"dzLKPZp1DJ"}],"key":"Iy7c7IkrU6"},{"type":"heading","depth":2,"position":{"start":{"line":20,"column":1},"end":{"line":20,"column":1}},"children":[{"type":"text","value":"Current Workflow","position":{"start":{"line":20,"column":1},"end":{"line":20,"column":1}},"key":"qKSSah3iFW"}],"identifier":"current-workflow","label":"Current Workflow","html_id":"current-workflow","implicit":true,"key":"PLzoZiUsdZ"},{"type":"heading","depth":3,"position":{"start":{"line":22,"column":1},"end":{"line":22,"column":1}},"children":[{"type":"text","value":"Phase 1: LaTeX Parsing ✅ COMPLETED","position":{"start":{"line":22,"column":1},"end":{"line":22,"column":1}},"key":"SaE2QMYavv"}],"identifier":"phase-1-latex-parsing-completed","label":"Phase 1: LaTeX Parsing ✅ COMPLETED","html_id":"phase-1-latex-parsing-completed","implicit":true,"key":"MOiaMHZ5iq"},{"type":"code","lang":"","value":"LaTeX Beamer → Universal_Document → PowerPoint API","position":{"start":{"line":23,"column":1},"end":{"line":25,"column":1}},"key":"kffW5zmfiB"},{"type":"paragraph","position":{"start":{"line":27,"column":1},"end":{"line":27,"column":1}},"children":[{"type":"strong","position":{"start":{"line":27,"column":1},"end":{"line":27,"column":1}},"children":[{"type":"text","value":"Implemented Approach","position":{"start":{"line":27,"column":1},"end":{"line":27,"column":1}},"key":"tG43rRdVmV"}],"key":"ZEzV7Tni9f"},{"type":"text","value":": AST-like parsing with regex-based extraction","position":{"start":{"line":27,"column":1},"end":{"line":27,"column":1}},"key":"TQDhtDXYM7"}],"key":"g4IKzQv2v6"},{"type":"list","ordered":false,"spread":false,"position":{"start":{"line":28,"column":1},"end":{"line":32,"column":1}},"children":[{"type":"listItem","spread":true,"position":{"start":{"line":28,"column":1},"end":{"line":28,"column":1}},"children":[{"type":"paragraph","children":[{"type":"text","value":"Parse LaTeX into hierarchical Universal_Document structure","position":{"start":{"line":28,"column":1},"end":{"line":28,"column":1}},"key":"ztA5f3xBb4"}],"key":"dZBWvMlqoI"}],"key":"X3Je07SbSw"},{"type":"listItem","spread":true,"position":{"start":{"line":29,"column":1},"end":{"line":29,"column":1}},"children":[{"type":"paragraph","children":[{"type":"text","value":"Extract frames, environments, and content","position":{"start":{"line":29,"column":1},"end":{"line":29,"column":1}},"key":"X0UwGSF1aV"}],"key":"gwtWuQCtdC"}],"key":"aSGdqh2qcK"},{"type":"listItem","spread":true,"position":{"start":{"line":30,"column":1},"end":{"line":30,"column":1}},"children":[{"type":"paragraph","children":[{"type":"text","value":"Build semantic understanding of document structure","position":{"start":{"line":30,"column":1},"end":{"line":30,"column":1}},"key":"plT7KHRhxX"}],"key":"Bo7PNuS3m8"}],"key":"RmiS73C5Cy"},{"type":"listItem","spread":true,"position":{"start":{"line":31,"column":1},"end":{"line":32,"column":1}},"children":[{"type":"paragraph","children":[{"type":"text","value":"Create format-agnostic data models","position":{"start":{"line":31,"column":1},"end":{"line":31,"column":1}},"key":"oJIhgPOqA9"}],"key":"aq3fXVLp6p"}],"key":"nKwmQ8vjOz"}],"key":"DnpchxX8fO"},{"type":"heading","depth":3,"position":{"start":{"line":33,"column":1},"end":{"line":33,"column":1}},"children":[{"type":"text","value":"Phase 2: Content Mapping ✅ COMPLETED","position":{"start":{"line":33,"column":1},"end":{"line":33,"column":1}},"key":"fBhg78s1Mp"}],"identifier":"phase-2-content-mapping-completed","label":"Phase 2: Content Mapping ✅ COMPLETED","html_id":"phase-2-content-mapping-completed","implicit":true,"key":"nylnYDT3fH"},{"type":"code","lang":"","value":"Universal_Document → Positioned Universal_Document","position":{"start":{"line":34,"column":1},"end":{"line":36,"column":1}},"key":"W3g5u3OMmo"},{"type":"paragraph","position":{"start":{"line":38,"column":1},"end":{"line":38,"column":1}},"children":[{"type":"strong","position":{"start":{"line":38,"column":1},"end":{"line":38,"column":1}},"children":[{"type":"text","value":"Implemented Features","position":{"start":{"line":38,"column":1},"end":{"line":38,"column":1}},"key":"IDtM4zuZnH"}],"key":"uqkOAkGetS"},{"type":"text","value":":","position":{"start":{"line":38,"column":1},"end":{"line":38,"column":1}},"key":"fbt66srbMQ"}],"key":"ymQn1BQ40c"},{"type":"list","ordered":false,"spread":false,"position":{"start":{"line":39,"column":1},"end":{"line":43,"column":1}},"children":[{"type":"listItem","spread":true,"position":{"start":{"line":39,"column":1},"end":{"line":39,"column":1}},"children":[{"type":"paragraph","children":[{"type":"text","value":"Layout-aware positioning calculations","position":{"start":{"line":39,"column":1},"end":{"line":39,"column":1}},"key":"qiPJB01Pye"}],"key":"vURwck6yPK"}],"key":"SsqYesItrJ"},{"type":"listItem","spread":true,"position":{"start":{"line":40,"column":1},"end":{"line":40,"column":1}},"children":[{"type":"paragraph","children":[{"type":"text","value":"Semantic element mapping (frames → slides, itemize → bullets, etc.)","position":{"start":{"line":40,"column":1},"end":{"line":40,"column":1}},"key":"nJTCONbCkt"}],"key":"nwpS8tH1zb"}],"key":"OkBEI4o6NU"},{"type":"listItem","spread":true,"position":{"start":{"line":41,"column":1},"end":{"line":41,"column":1}},"children":[{"type":"paragraph","children":[{"type":"text","value":"Position assignment based on slide layout types","position":{"start":{"line":41,"column":1},"end":{"line":41,"column":1}},"key":"iVuqR5T4sH"}],"key":"snJfNtMJkJ"}],"key":"x2Rc7hbtga"},{"type":"listItem","spread":true,"position":{"start":{"line":42,"column":1},"end":{"line":43,"column":1}},"children":[{"type":"paragraph","children":[{"type":"text","value":"Image path resolution with source context","position":{"start":{"line":42,"column":1},"end":{"line":42,"column":1}},"key":"QHNDrStcCi"}],"key":"coDVix6wXQ"}],"key":"EqCXvfTCjY"}],"key":"ym7sM989BK"},{"type":"heading","depth":3,"position":{"start":{"line":44,"column":1},"end":{"line":44,"column":1}},"children":[{"type":"text","value":"Phase 3: PowerPoint Generation ✅ COMPLETED","position":{"start":{"line":44,"column":1},"end":{"line":44,"column":1}},"key":"OLVbh8kuUs"}],"identifier":"phase-3-powerpoint-generation-completed","label":"Phase 3: PowerPoint Generation ✅ COMPLETED","html_id":"phase-3-powerpoint-generation-completed","implicit":true,"key":"RvBlgrfOI0"},{"type":"code","lang":"","value":"Positioned Universal_Document → python-pptx API → .pptx File","position":{"start":{"line":45,"column":1},"end":{"line":47,"column":1}},"key":"HYuPBEOFfy"},{"type":"paragraph","position":{"start":{"line":49,"column":1},"end":{"line":49,"column":1}},"children":[{"type":"strong","position":{"start":{"line":49,"column":1},"end":{"line":49,"column":1}},"children":[{"type":"text","value":"Implemented Features","position":{"start":{"line":49,"column":1},"end":{"line":49,"column":1}},"key":"jh5xTjneOr"}],"key":"pisdrqZW3E"},{"type":"text","value":":","position":{"start":{"line":49,"column":1},"end":{"line":49,"column":1}},"key":"CF8m7RBdYQ"}],"key":"dnGrETziaN"},{"type":"list","ordered":false,"spread":false,"position":{"start":{"line":50,"column":1},"end":{"line":55,"column":1}},"children":[{"type":"listItem","spread":true,"position":{"start":{"line":50,"column":1},"end":{"line":50,"column":1}},"children":[{"type":"paragraph","children":[{"type":"text","value":"Native PowerPoint placeholder usage","position":{"start":{"line":50,"column":1},"end":{"line":50,"column":1}},"key":"h0bzTSgb4S"}],"key":"iDBGyjgIF3"}],"key":"eRqdT7oDzr"},{"type":"listItem","spread":true,"position":{"start":{"line":51,"column":1},"end":{"line":51,"column":1}},"children":[{"type":"paragraph","children":[{"type":"text","value":"Smart text box positioning with fallbacks","position":{"start":{"line":51,"column":1},"end":{"line":51,"column":1}},"key":"dUetuwWN7B"}],"key":"nsc4pMv8xE"}],"key":"k5nCF43uA9"},{"type":"listItem","spread":true,"position":{"start":{"line":52,"column":1},"end":{"line":52,"column":1}},"children":[{"type":"paragraph","children":[{"type":"text","value":"Font size handling with proper Pt() units","position":{"start":{"line":52,"column":1},"end":{"line":52,"column":1}},"key":"IOQvxQ4gwP"}],"key":"HRDMzAU8vd"}],"key":"vqO1xXR5pk"},{"type":"listItem","spread":true,"position":{"start":{"line":53,"column":1},"end":{"line":53,"column":1}},"children":[{"type":"paragraph","children":[{"type":"text","value":"Image embedding and path resolution","position":{"start":{"line":53,"column":1},"end":{"line":53,"column":1}},"key":"oihfLu2GTj"}],"key":"zg7IWJGfHw"}],"key":"f9qCCHSah3"},{"type":"listItem","spread":true,"position":{"start":{"line":54,"column":1},"end":{"line":55,"column":1}},"children":[{"type":"paragraph","children":[{"type":"text","value":"Theme system with multiple PowerPoint themes","position":{"start":{"line":54,"column":1},"end":{"line":54,"column":1}},"key":"YslQ2FNuw7"}],"key":"MJpb2cZAOe"}],"key":"a2pIQAA5KM"}],"key":"HaPQREhao2"},{"type":"heading","depth":2,"position":{"start":{"line":56,"column":1},"end":{"line":56,"column":1}},"children":[{"type":"text","value":"Next Phase Workflow","position":{"start":{"line":56,"column":1},"end":{"line":56,"column":1}},"key":"hMjSOsAUhp"}],"identifier":"next-phase-workflow","label":"Next Phase Workflow","html_id":"next-phase-workflow","implicit":true,"key":"dwkZV8TfSz"},{"type":"heading","depth":3,"position":{"start":{"line":58,"column":1},"end":{"line":58,"column":1}},"children":[{"type":"text","value":"Phase 4: Advanced Features 🔄 IN PROGRESS","position":{"start":{"line":58,"column":1},"end":{"line":58,"column":1}},"key":"nu6vvgrNQX"}],"identifier":"phase-4-advanced-features-in-progress","label":"Phase 4: Advanced Features 🔄 IN PROGRESS","html_id":"phase-4-advanced-features-in-progress","implicit":true,"key":"btVVP1JjfP"},{"type":"code","lang":"","value":"Enhanced LaTeX → Extended Universal_Document → Advanced PowerPoint","position":{"start":{"line":59,"column":1},"end":{"line":61,"column":1}},"key":"Hn8eHeO2NY"},{"type":"paragraph","position":{"start":{"line":63,"column":1},"end":{"line":63,"column":1}},"children":[{"type":"strong","position":{"start":{"line":63,"column":1},"end":{"line":63,"column":1}},"children":[{"type":"text","value":"Planned Enhancements","position":{"start":{"line":63,"column":1},"end":{"line":63,"column":1}},"key":"CDhh7rwMXj"}],"key":"QUyx66NZE7"},{"type":"text","value":":","position":{"start":{"line":63,"column":1},"end":{"line":63,"column":1}},"key":"EZmjXL7i0j"}],"key":"SRFT3RfAdc"},{"type":"list","ordered":false,"spread":false,"position":{"start":{"line":64,"column":1},"end":{"line":69,"column":1}},"children":[{"type":"listItem","spread":true,"position":{"start":{"line":64,"column":1},"end":{"line":64,"column":1}},"children":[{"type":"paragraph","children":[{"type":"text","value":"Math equation rendering (as images/text)","position":{"start":{"line":64,"column":1},"end":{"line":64,"column":1}},"key":"Tp6kPbVqA6"}],"key":"N8DwsYfjS0"}],"key":"d3FqkQE13p"},{"type":"listItem","spread":true,"position":{"start":{"line":65,"column":1},"end":{"line":65,"column":1}},"children":[{"type":"paragraph","children":[{"type":"text","value":"TikZ diagram conversion","position":{"start":{"line":65,"column":1},"end":{"line":65,"column":1}},"key":"JFOOKwRcrs"}],"key":"xnBrRCadRf"}],"key":"Nh38fhS8hU"},{"type":"listItem","spread":true,"position":{"start":{"line":66,"column":1},"end":{"line":66,"column":1}},"children":[{"type":"paragraph","children":[{"type":"text","value":"Custom LaTeX command support","position":{"start":{"line":66,"column":1},"end":{"line":66,"column":1}},"key":"MHXgbOy1ZJ"}],"key":"miMPmB465J"}],"key":"YYKpym100h"},{"type":"listItem","spread":true,"position":{"start":{"line":67,"column":1},"end":{"line":67,"column":1}},"children":[{"type":"paragraph","children":[{"type":"text","value":"Beamer overlay specifications","position":{"start":{"line":67,"column":1},"end":{"line":67,"column":1}},"key":"S6OLXifWcd"}],"key":"WFLM77aE2v"}],"key":"kRN1f7kCSK"},{"type":"listItem","spread":true,"position":{"start":{"line":68,"column":1},"end":{"line":69,"column":1}},"children":[{"type":"paragraph","children":[{"type":"text","value":"Advanced table formatting","position":{"start":{"line":68,"column":1},"end":{"line":68,"column":1}},"key":"c3hHiLMTGc"}],"key":"LT6b6m0ODy"}],"key":"mtUeI28s9g"}],"key":"FEOI3zuKVf"},{"type":"heading","depth":3,"position":{"start":{"line":70,"column":1},"end":{"line":70,"column":1}},"children":[{"type":"text","value":"Phase 5: Multi-Format Support 📋 PLANNED","position":{"start":{"line":70,"column":1},"end":{"line":70,"column":1}},"key":"g8Cf9ESpJa"}],"identifier":"phase-5-multi-format-support-planned","label":"Phase 5: Multi-Format Support 📋 PLANNED","html_id":"phase-5-multi-format-support-planned","implicit":true,"key":"LLXbPRwkNf"},{"type":"code","lang":"","value":"Universal_Document → Multiple Output Formats","position":{"start":{"line":71,"column":1},"end":{"line":73,"column":1}},"key":"k6Sxw6VT4Q"},{"type":"paragraph","position":{"start":{"line":75,"column":1},"end":{"line":75,"column":1}},"children":[{"type":"strong","position":{"start":{"line":75,"column":1},"end":{"line":75,"column":1}},"children":[{"type":"text","value":"Target Formats","position":{"start":{"line":75,"column":1},"end":{"line":75,"column":1}},"key":"WB0KeixlWA"}],"key":"hWzKtn0t7w"},{"type":"text","value":":","position":{"start":{"line":75,"column":1},"end":{"line":75,"column":1}},"key":"kOtRqPW1MA"}],"key":"MKddIBvL3d"},{"type":"list","ordered":false,"spread":false,"position":{"start":{"line":76,"column":1},"end":{"line":80,"column":1}},"children":[{"type":"listItem","spread":true,"position":{"start":{"line":76,"column":1},"end":{"line":76,"column":1}},"children":[{"type":"paragraph","children":[{"type":"text","value":"PowerPoint → LaTeX (round-trip conversion)","position":{"start":{"line":76,"column":1},"end":{"line":76,"column":1}},"key":"OzqgMFEvEc"}],"key":"vtrysaeLyS"}],"key":"b9fS3GAwvq"},{"type":"listItem","spread":true,"position":{"start":{"line":77,"column":1},"end":{"line":77,"column":1}},"children":[{"type":"paragraph","children":[{"type":"text","value":"Markdown → PowerPoint","position":{"start":{"line":77,"column":1},"end":{"line":77,"column":1}},"key":"XdR47Qv7Bt"}],"key":"mD0JWGjzwE"}],"key":"zpqOWIvE51"},{"type":"listItem","spread":true,"position":{"start":{"line":78,"column":1},"end":{"line":78,"column":1}},"children":[{"type":"paragraph","children":[{"type":"text","value":"HTML/Web presentations","position":{"start":{"line":78,"column":1},"end":{"line":78,"column":1}},"key":"yHi777Cifr"}],"key":"HWahgBl1qT"}],"key":"w20zB0uRnH"},{"type":"listItem","spread":true,"position":{"start":{"line":79,"column":1},"end":{"line":80,"column":1}},"children":[{"type":"paragraph","children":[{"type":"text","value":"PDF export","position":{"start":{"line":79,"column":1},"end":{"line":79,"column":1}},"key":"d3YBQkhuDy"}],"key":"UfTMfOT52r"}],"key":"sccMXnlIEg"}],"key":"QU4soIUrTI"},{"type":"heading","depth":3,"position":{"start":{"line":81,"column":1},"end":{"line":81,"column":1}},"children":[{"type":"text","value":"Phase 6: Production Features 📋 PLANNED","position":{"start":{"line":81,"column":1},"end":{"line":81,"column":1}},"key":"TBjpmbTEFC"}],"identifier":"phase-6-production-features-planned","label":"Phase 6: Production Features 📋 PLANNED","html_id":"phase-6-production-features-planned","implicit":true,"key":"yjuAUfQx9G"},{"type":"code","lang":"","value":"Enhanced System → Enterprise-Ready Solution","position":{"start":{"line":82,"column":1},"end":{"line":84,"column":1}},"key":"rFHWdGexMz"},{"type":"paragraph","position":{"start":{"line":86,"column":1},"end":{"line":86,"column":1}},"children":[{"type":"strong","position":{"start":{"line":86,"column":1},"end":{"line":86,"column":1}},"children":[{"type":"text","value":"Enterprise Features","position":{"start":{"line":86,"column":1},"end":{"line":86,"column":1}},"key":"XoLdmbycgj"}],"key":"XNSOTtk5MK"},{"type":"text","value":":","position":{"start":{"line":86,"column":1},"end":{"line":86,"column":1}},"key":"KwKHCrY2mn"}],"key":"DRlajdo0GB"},{"type":"list","ordered":false,"spread":false,"position":{"start":{"line":87,"column":1},"end":{"line":92,"column":1}},"children":[{"type":"listItem","spread":true,"position":{"start":{"line":87,"column":1},"end":{"line":87,"column":1}},"children":[{"type":"paragraph","children":[{"type":"text","value":"Template system with custom designs","position":{"start":{"line":87,"column":1},"end":{"line":87,"column":1}},"key":"StVNjyZH7L"}],"key":"e9Nd3vlB7U"}],"key":"H07uw9AD6W"},{"type":"listItem","spread":true,"position":{"start":{"line":88,"column":1},"end":{"line":88,"column":1}},"children":[{"type":"paragraph","children":[{"type":"text","value":"Plugin architecture for extensibility","position":{"start":{"line":88,"column":1},"end":{"line":88,"column":1}},"key":"gRGtfDel2w"}],"key":"VqIpehowcU"}],"key":"qDgS31jVNd"},{"type":"listItem","spread":true,"position":{"start":{"line":89,"column":1},"end":{"line":89,"column":1}},"children":[{"type":"paragraph","children":[{"type":"text","value":"Performance optimizations","position":{"start":{"line":89,"column":1},"end":{"line":89,"column":1}},"key":"J4FhWaZpYn"}],"key":"qhIZnrotXN"}],"key":"SQl8AFHk5Z"},{"type":"listItem","spread":true,"position":{"start":{"line":90,"column":1},"end":{"line":90,"column":1}},"children":[{"type":"paragraph","children":[{"type":"text","value":"Batch processing capabilities","position":{"start":{"line":90,"column":1},"end":{"line":90,"column":1}},"key":"BJV0zaimjB"}],"key":"sLGkMnIllM"}],"key":"KorKwP2Whv"},{"type":"listItem","spread":true,"position":{"start":{"line":91,"column":1},"end":{"line":92,"column":1}},"children":[{"type":"paragraph","children":[{"type":"text","value":"API for integration","position":{"start":{"line":91,"column":1},"end":{"line":91,"column":1}},"key":"XJkd74Qano"}],"key":"LedY1XOr5s"}],"key":"IHipB2FIaL"}],"key":"dlOlGAH8mL"},{"type":"heading","depth":2,"position":{"start":{"line":93,"column":1},"end":{"line":93,"column":1}},"children":[{"type":"text","value":"Implementation Insights & Lessons Learned","position":{"start":{"line":93,"column":1},"end":{"line":93,"column":1}},"key":"dWly3yPtE9"}],"identifier":"implementation-insights-lessons-learned","label":"Implementation Insights & Lessons Learned","html_id":"implementation-insights-lessons-learned","implicit":true,"key":"iBbP1XoboF"},{"type":"heading","depth":3,"position":{"start":{"line":95,"column":1},"end":{"line":95,"column":1}},"children":[{"type":"text","value":"1. Positioning Architecture","position":{"start":{"line":95,"column":1},"end":{"line":95,"column":1}},"key":"n5lyTrJUFA"}],"identifier":"id-1-positioning-architecture","label":"1. Positioning Architecture","html_id":"id-1-positioning-architecture","implicit":true,"key":"wyykYKPLxr"},{"type":"paragraph","position":{"start":{"line":97,"column":1},"end":{"line":97,"column":1}},"children":[{"type":"strong","position":{"start":{"line":97,"column":1},"end":{"line":97,"column":1}},"children":[{"type":"text","value":"Initial Problem","position":{"start":{"line":97,"column":1},"end":{"line":97,"column":1}},"key":"FyrNOjtYmf"}],"key":"sHTt5dBhTU"},{"type":"text","value":": All elements were overlapping because they were positioned at the same coordinates.","position":{"start":{"line":97,"column":1},"end":{"line":97,"column":1}},"key":"oC8abpqLbf"}],"key":"DE9XM42JBI"},{"type":"paragraph","position":{"start":{"line":99,"column":1},"end":{"line":99,"column":1}},"children":[{"type":"strong","position":{"start":{"line":99,"column":1},"end":{"line":99,"column":1}},"children":[{"type":"text","value":"Solution","position":{"start":{"line":99,"column":1},"end":{"line":99,"column":1}},"key":"F0gjGHMnoF"}],"key":"sBWEW7eOxN"},{"type":"text","value":": Implemented a two-layer positioning system:","position":{"start":{"line":99,"column":1},"end":{"line":99,"column":1}},"key":"zdNdo3g5wg"}],"key":"Sm8PHDp4Vu"},{"type":"list","ordered":false,"spread":false,"position":{"start":{"line":100,"column":1},"end":{"line":102,"column":1}},"children":[{"type":"listItem","spread":true,"position":{"start":{"line":100,"column":1},"end":{"line":100,"column":1}},"children":[{"type":"paragraph","children":[{"type":"strong","position":{"start":{"line":100,"column":1},"end":{"line":100,"column":1}},"children":[{"type":"text","value":"Content Mapper","position":{"start":{"line":100,"column":1},"end":{"line":100,"column":1}},"key":"Za46SC0qaJ"}],"key":"c8K0SOZd9x"},{"type":"text","value":": Calculates semantic positions based on layout type","position":{"start":{"line":100,"column":1},"end":{"line":100,"column":1}},"key":"Uh7xvkJ7Bi"}],"key":"BN2ZOOifQI"}],"key":"CzJHqL6KTP"},{"type":"listItem","spread":true,"position":{"start":{"line":101,"column":1},"end":{"line":102,"column":1}},"children":[{"type":"paragraph","children":[{"type":"strong","position":{"start":{"line":101,"column":1},"end":{"line":101,"column":1}},"children":[{"type":"text","value":"PowerPoint Builder","position":{"start":{"line":101,"column":1},"end":{"line":101,"column":1}},"key":"dlQSLrKBPU"}],"key":"HJAYu3vszr"},{"type":"text","value":": Renders elements at calculated positions","position":{"start":{"line":101,"column":1},"end":{"line":101,"column":1}},"key":"KKIXXUXEYO"}],"key":"zy37VUiWJw"}],"key":"eXeTWIYLJH"}],"key":"e6KaVOCKhy"},{"type":"paragraph","position":{"start":{"line":103,"column":1},"end":{"line":103,"column":1}},"children":[{"type":"strong","position":{"start":{"line":103,"column":1},"end":{"line":103,"column":1}},"children":[{"type":"text","value":"Key Insight","position":{"start":{"line":103,"column":1},"end":{"line":103,"column":1}},"key":"ytdx11NTjV"}],"key":"y2p8FlYlJG"},{"type":"text","value":": Separation of concerns is crucial. The mapper handles “what goes where” while the builder handles “how to render.”","position":{"start":{"line":103,"column":1},"end":{"line":103,"column":1}},"key":"o7rAzlI7js"}],"key":"JDNDSWP0tK"},{"type":"heading","depth":3,"position":{"start":{"line":105,"column":1},"end":{"line":105,"column":1}},"children":[{"type":"text","value":"2. Native PowerPoint Placeholder Usage","position":{"start":{"line":105,"column":1},"end":{"line":105,"column":1}},"key":"yGqqqICKht"}],"identifier":"id-2-native-powerpoint-placeholder-usage","label":"2. Native PowerPoint Placeholder Usage","html_id":"id-2-native-powerpoint-placeholder-usage","implicit":true,"key":"PCJUwR1awO"},{"type":"paragraph","position":{"start":{"line":107,"column":1},"end":{"line":107,"column":1}},"children":[{"type":"strong","position":{"start":{"line":107,"column":1},"end":{"line":107,"column":1}},"children":[{"type":"text","value":"Initial Problem","position":{"start":{"line":107,"column":1},"end":{"line":107,"column":1}},"key":"BeKzXfwfD4"}],"key":"DbWSHCGo1f"},{"type":"text","value":": Content was dumped into text boxes, causing “dashed boxes” (PowerPoint’s default placeholders) to remain unused.","position":{"start":{"line":107,"column":1},"end":{"line":107,"column":1}},"key":"MM0mqtDFpv"}],"key":"emFzBI3Lmt"},{"type":"paragraph","position":{"start":{"line":109,"column":1},"end":{"line":109,"column":1}},"children":[{"type":"strong","position":{"start":{"line":109,"column":1},"end":{"line":109,"column":1}},"children":[{"type":"text","value":"Solution","position":{"start":{"line":109,"column":1},"end":{"line":109,"column":1}},"key":"pS0ISctrju"}],"key":"WWR7QomDnT"},{"type":"text","value":": Smart placeholder usage:","position":{"start":{"line":109,"column":1},"end":{"line":109,"column":1}},"key":"mbYWZk7TCW"}],"key":"SIYZHaOE7Q"},{"type":"code","lang":"python","value":"# Use native content placeholder for first element\nif not content_placeholder_used and slide_obj.placeholders:\n    content_placeholder_used = self._add_text_to_placeholder(slide_obj, element, config, preserve_colors)\nelse:\n    self._add_text_element(slide_obj, element, config, preserve_colors)","position":{"start":{"line":110,"column":1},"end":{"line":116,"column":1}},"key":"P8SBh5xbup"},{"type":"paragraph","position":{"start":{"line":118,"column":1},"end":{"line":118,"column":1}},"children":[{"type":"strong","position":{"start":{"line":118,"column":1},"end":{"line":118,"column":1}},"children":[{"type":"text","value":"Key Insight","position":{"start":{"line":118,"column":1},"end":{"line":118,"column":1}},"key":"nyBdkeanHs"}],"key":"BidaJjOCUN"},{"type":"text","value":": PowerPoint layouts work best when you respect their native structure. Use placeholders first, fall back to positioned text boxes.","position":{"start":{"line":118,"column":1},"end":{"line":118,"column":1}},"key":"GIItT7COHZ"}],"key":"CRd3fqiv4e"},{"type":"heading","depth":3,"position":{"start":{"line":120,"column":1},"end":{"line":120,"column":1}},"children":[{"type":"text","value":"3. Font Size Handling","position":{"start":{"line":120,"column":1},"end":{"line":120,"column":1}},"key":"bh213H3n70"}],"identifier":"id-3-font-size-handling","label":"3. Font Size Handling","html_id":"id-3-font-size-handling","implicit":true,"key":"hcgYMvAxuR"},{"type":"paragraph","position":{"start":{"line":122,"column":1},"end":{"line":122,"column":1}},"children":[{"type":"strong","position":{"start":{"line":122,"column":1},"end":{"line":122,"column":1}},"children":[{"type":"text","value":"Problem","position":{"start":{"line":122,"column":1},"end":{"line":122,"column":1}},"key":"ITAwoiZWUK"}],"key":"zfxi3JgY3R"},{"type":"text","value":": Raw integers caused “value must be in range” errors with python-pptx.","position":{"start":{"line":122,"column":1},"end":{"line":122,"column":1}},"key":"jdy0mL0Ts6"}],"key":"MbpQk090fY"},{"type":"paragraph","position":{"start":{"line":124,"column":1},"end":{"line":124,"column":1}},"children":[{"type":"strong","position":{"start":{"line":124,"column":1},"end":{"line":124,"column":1}},"children":[{"type":"text","value":"Solution","position":{"start":{"line":124,"column":1},"end":{"line":124,"column":1}},"key":"TPSrc1C24m"}],"key":"jWPp71cRVp"},{"type":"text","value":": Use proper Pt() units:","position":{"start":{"line":124,"column":1},"end":{"line":124,"column":1}},"key":"yGPZy3rWes"}],"key":"ChTmwHOUbi"},{"type":"code","lang":"python","value":"from pptx.util import Pt\np.font.size = Pt(font_size)  # Instead of p.font.size = font_size","position":{"start":{"line":125,"column":1},"end":{"line":128,"column":1}},"key":"GNztYwKebv"},{"type":"paragraph","position":{"start":{"line":130,"column":1},"end":{"line":130,"column":1}},"children":[{"type":"strong","position":{"start":{"line":130,"column":1},"end":{"line":130,"column":1}},"children":[{"type":"text","value":"Key Insight","position":{"start":{"line":130,"column":1},"end":{"line":130,"column":1}},"key":"uDQOIo7i6c"}],"key":"FANUHkJkFC"},{"type":"text","value":": python-pptx has specific unit requirements. Always use the provided utility functions.","position":{"start":{"line":130,"column":1},"end":{"line":130,"column":1}},"key":"zTgh45m8oh"}],"key":"aXe1665Hse"},{"type":"heading","depth":3,"position":{"start":{"line":132,"column":1},"end":{"line":132,"column":1}},"children":[{"type":"text","value":"4. Image Path Resolution","position":{"start":{"line":132,"column":1},"end":{"line":132,"column":1}},"key":"qrnZT2bnQ7"}],"identifier":"id-4-image-path-resolution","label":"4. Image Path Resolution","html_id":"id-4-image-path-resolution","implicit":true,"key":"qVR8BeEu1h"},{"type":"paragraph","position":{"start":{"line":134,"column":1},"end":{"line":134,"column":1}},"children":[{"type":"strong","position":{"start":{"line":134,"column":1},"end":{"line":134,"column":1}},"children":[{"type":"text","value":"Problem","position":{"start":{"line":134,"column":1},"end":{"line":134,"column":1}},"key":"BbjfSKurer"}],"key":"Cs4pFtYdBI"},{"type":"text","value":": Images were looked for in the wrong directory (project root instead of LaTeX file directory).","position":{"start":{"line":134,"column":1},"end":{"line":134,"column":1}},"key":"gzawWDcVHb"}],"key":"WyzMaNqQW2"},{"type":"paragraph","position":{"start":{"line":136,"column":1},"end":{"line":136,"column":1}},"children":[{"type":"strong","position":{"start":{"line":136,"column":1},"end":{"line":136,"column":1}},"children":[{"type":"text","value":"Solution","position":{"start":{"line":136,"column":1},"end":{"line":136,"column":1}},"key":"nRAMIhm8E6"}],"key":"rzE1hxZa5I"},{"type":"text","value":": Pass source path through the conversion chain:","position":{"start":{"line":136,"column":1},"end":{"line":136,"column":1}},"key":"qrgu43IclG"}],"key":"ldyShRwXQd"},{"type":"code","lang":"python","value":"# Core passes source path to builder\nbuild_options = {**options.custom_settings, 'source_path': document.source_path}\nsuccess = builder.build_presentation(slide_structures, output_path, **build_options)","position":{"start":{"line":137,"column":1},"end":{"line":141,"column":1}},"key":"PdCzTgFXvg"},{"type":"paragraph","position":{"start":{"line":143,"column":1},"end":{"line":143,"column":1}},"children":[{"type":"strong","position":{"start":{"line":143,"column":1},"end":{"line":143,"column":1}},"children":[{"type":"text","value":"Key Insight","position":{"start":{"line":143,"column":1},"end":{"line":143,"column":1}},"key":"tYxAUXb1MO"}],"key":"oPvs682aoy"},{"type":"text","value":": Context matters. The builder needs to know where the source file was located to resolve relative paths.","position":{"start":{"line":143,"column":1},"end":{"line":143,"column":1}},"key":"MpszvUKKca"}],"key":"P9ewgZiEAb"},{"type":"heading","depth":3,"position":{"start":{"line":145,"column":1},"end":{"line":145,"column":1}},"children":[{"type":"text","value":"5. Layout System Design","position":{"start":{"line":145,"column":1},"end":{"line":145,"column":1}},"key":"mbC2DVmEIc"}],"identifier":"id-5-layout-system-design","label":"5. Layout System Design","html_id":"id-5-layout-system-design","implicit":true,"key":"vwetqwqsLW"},{"type":"paragraph","position":{"start":{"line":147,"column":1},"end":{"line":147,"column":1}},"children":[{"type":"strong","position":{"start":{"line":147,"column":1},"end":{"line":147,"column":1}},"children":[{"type":"text","value":"Implementation","position":{"start":{"line":147,"column":1},"end":{"line":147,"column":1}},"key":"J6eVXBK0YO"}],"key":"YM2cOVgciS"},{"type":"text","value":": Content mapper calculates positions based on layout constants:","position":{"start":{"line":147,"column":1},"end":{"line":147,"column":1}},"key":"toxF6EfALJ"}],"key":"LSjPUvPYDR"},{"type":"code","lang":"python","value":"MARGIN_LEFT = 1.0\nMARGIN_TOP = 2.5  # Below title\nELEMENT_SPACING = 0.4\nCONTENT_WIDTH = SLIDE_WIDTH - MARGIN_LEFT - MARGIN_RIGHT","position":{"start":{"line":148,"column":1},"end":{"line":153,"column":1}},"key":"BzWIhPI9aV"},{"type":"paragraph","position":{"start":{"line":155,"column":1},"end":{"line":155,"column":1}},"children":[{"type":"strong","position":{"start":{"line":155,"column":1},"end":{"line":155,"column":1}},"children":[{"type":"text","value":"Key Insight","position":{"start":{"line":155,"column":1},"end":{"line":155,"column":1}},"key":"eMZycID7Iu"}],"key":"k7KnEq3P4k"},{"type":"text","value":": Layout calculations should be format-agnostic in the mapper, with format-specific rendering in the builder.","position":{"start":{"line":155,"column":1},"end":{"line":155,"column":1}},"key":"bFcPTh8FfJ"}],"key":"GsVe0CrvV2"},{"type":"heading","depth":2,"position":{"start":{"line":157,"column":1},"end":{"line":157,"column":1}},"children":[{"type":"text","value":"Architecture Refinements","position":{"start":{"line":157,"column":1},"end":{"line":157,"column":1}},"key":"SL4191aFmq"}],"identifier":"architecture-refinements","label":"Architecture Refinements","html_id":"architecture-refinements","implicit":true,"key":"Ajceuhw58M"},{"type":"heading","depth":3,"position":{"start":{"line":159,"column":1},"end":{"line":159,"column":1}},"children":[{"type":"text","value":"Current Data Flow (Revised)","position":{"start":{"line":159,"column":1},"end":{"line":159,"column":1}},"key":"fuzRcgNARu"}],"identifier":"current-data-flow-revised","label":"Current Data Flow (Revised)","html_id":"current-data-flow-revised","implicit":true,"key":"HLCNYqoJqH"},{"type":"code","lang":"","value":"presentation.tex\n    ↓\nLaTeXParser.parse()\n    ↓\nUniversal_Document {\n  metadata: {...},\n  frames: [Universal_Frame {\n    title: \"Slide Title\",\n    elements: [Universal_Element {\n      element_type: Element_Type.TEXT,\n      content: \"content\",\n      position: Position {x: 1.0, y: 2.5, width: 8.0, height: 0.5}\n    }]\n  }]\n}\n    ↓\nContentMapper.map()  # ← NEW: Adds positioning\n    ↓\nPositioned Universal_Document\n    ↓\nPowerPointBuilder.build()  # ← ENHANCED: Uses placeholders + positioning\n    ↓\npresentation.pptx","position":{"start":{"line":160,"column":1},"end":{"line":184,"column":1}},"key":"rkswHp5Wnv"},{"type":"heading","depth":3,"position":{"start":{"line":186,"column":1},"end":{"line":186,"column":1}},"children":[{"type":"text","value":"Key Architectural Principles","position":{"start":{"line":186,"column":1},"end":{"line":186,"column":1}},"key":"C5fficVJLj"}],"identifier":"key-architectural-principles","label":"Key Architectural Principles","html_id":"key-architectural-principles","implicit":true,"key":"MnmCSv6tMb"},{"type":"list","ordered":true,"start":1,"spread":false,"position":{"start":{"line":188,"column":1},"end":{"line":193,"column":1}},"children":[{"type":"listItem","spread":true,"position":{"start":{"line":188,"column":1},"end":{"line":188,"column":1}},"children":[{"type":"paragraph","children":[{"type":"strong","position":{"start":{"line":188,"column":1},"end":{"line":188,"column":1}},"children":[{"type":"text","value":"Universal Models","position":{"start":{"line":188,"column":1},"end":{"line":188,"column":1}},"key":"ShYxZPtTQH"}],"key":"OBfNLiI9YF"},{"type":"text","value":": Format-agnostic data structures","position":{"start":{"line":188,"column":1},"end":{"line":188,"column":1}},"key":"LloaXsOFW9"}],"key":"Rs4v8vXi5q"}],"key":"aKK6w35JIV"},{"type":"listItem","spread":true,"position":{"start":{"line":189,"column":1},"end":{"line":189,"column":1}},"children":[{"type":"paragraph","children":[{"type":"strong","position":{"start":{"line":189,"column":1},"end":{"line":189,"column":1}},"children":[{"type":"text","value":"Smart Positioning","position":{"start":{"line":189,"column":1},"end":{"line":189,"column":1}},"key":"Bj3kJqQDhx"}],"key":"SuWgob1vBc"},{"type":"text","value":": Layout calculations in mapper, rendering in builder","position":{"start":{"line":189,"column":1},"end":{"line":189,"column":1}},"key":"GI9s2PxkJ4"}],"key":"NJm9vVngnI"}],"key":"PgwVIJxqmE"},{"type":"listItem","spread":true,"position":{"start":{"line":190,"column":1},"end":{"line":190,"column":1}},"children":[{"type":"paragraph","children":[{"type":"strong","position":{"start":{"line":190,"column":1},"end":{"line":190,"column":1}},"children":[{"type":"text","value":"Native Integration","position":{"start":{"line":190,"column":1},"end":{"line":190,"column":1}},"key":"TR84fHRsK8"}],"key":"wWEMoroqV8"},{"type":"text","value":": Respect target format’s native structures (placeholders)","position":{"start":{"line":190,"column":1},"end":{"line":190,"column":1}},"key":"mivqK8b9QE"}],"key":"WB7wHdBlXv"}],"key":"WkBk6LDwMH"},{"type":"listItem","spread":true,"position":{"start":{"line":191,"column":1},"end":{"line":191,"column":1}},"children":[{"type":"paragraph","children":[{"type":"strong","position":{"start":{"line":191,"column":1},"end":{"line":191,"column":1}},"children":[{"type":"text","value":"Context Awareness","position":{"start":{"line":191,"column":1},"end":{"line":191,"column":1}},"key":"lLtZzEwgtq"}],"key":"ufTbvaB0zN"},{"type":"text","value":": Pass source context through the conversion chain","position":{"start":{"line":191,"column":1},"end":{"line":191,"column":1}},"key":"TLauensjZI"}],"key":"zCZxAsPMxV"}],"key":"d7lrAKCn4m"},{"type":"listItem","spread":true,"position":{"start":{"line":192,"column":1},"end":{"line":193,"column":1}},"children":[{"type":"paragraph","children":[{"type":"strong","position":{"start":{"line":192,"column":1},"end":{"line":192,"column":1}},"children":[{"type":"text","value":"Graceful Degradation","position":{"start":{"line":192,"column":1},"end":{"line":192,"column":1}},"key":"Ps92LBgBVF"}],"key":"c7Klzitw2S"},{"type":"text","value":": Fallbacks when ideal approaches fail","position":{"start":{"line":192,"column":1},"end":{"line":192,"column":1}},"key":"l6kw2Pp0bp"}],"key":"yOD5dUSN2p"}],"key":"fC0CM3pYFR"}],"key":"WoN3jHv6rC"},{"type":"heading","depth":2,"position":{"start":{"line":194,"column":1},"end":{"line":194,"column":1}},"children":[{"type":"text","value":"Performance Considerations","position":{"start":{"line":194,"column":1},"end":{"line":194,"column":1}},"key":"JJRultEBUv"}],"identifier":"performance-considerations","label":"Performance Considerations","html_id":"performance-considerations","implicit":true,"key":"vURwks1AHF"},{"type":"heading","depth":3,"position":{"start":{"line":196,"column":1},"end":{"line":196,"column":1}},"children":[{"type":"text","value":"Current Bottlenecks","position":{"start":{"line":196,"column":1},"end":{"line":196,"column":1}},"key":"hE2FuFtzPV"}],"identifier":"current-bottlenecks","label":"Current Bottlenecks","html_id":"current-bottlenecks","implicit":true,"key":"Z1pq5anC48"},{"type":"list","ordered":true,"start":1,"spread":false,"position":{"start":{"line":197,"column":1},"end":{"line":200,"column":1}},"children":[{"type":"listItem","spread":true,"position":{"start":{"line":197,"column":1},"end":{"line":197,"column":1}},"children":[{"type":"paragraph","children":[{"type":"strong","position":{"start":{"line":197,"column":1},"end":{"line":197,"column":1}},"children":[{"type":"text","value":"LaTeX Parsing","position":{"start":{"line":197,"column":1},"end":{"line":197,"column":1}},"key":"JrRszCDk60"}],"key":"F4Gd4aZoES"},{"type":"text","value":": Complex regex operations","position":{"start":{"line":197,"column":1},"end":{"line":197,"column":1}},"key":"v2HvfIHwuj"}],"key":"PV7SCwvw5O"}],"key":"u343l10YR2"},{"type":"listItem","spread":true,"position":{"start":{"line":198,"column":1},"end":{"line":198,"column":1}},"children":[{"type":"paragraph","children":[{"type":"strong","position":{"start":{"line":198,"column":1},"end":{"line":198,"column":1}},"children":[{"type":"text","value":"Image Processing","position":{"start":{"line":198,"column":1},"end":{"line":198,"column":1}},"key":"zoFXjJxbTu"}],"key":"vGIHTZPDsF"},{"type":"text","value":": File I/O for each image","position":{"start":{"line":198,"column":1},"end":{"line":198,"column":1}},"key":"szMXVOJGxH"}],"key":"K0tpl8GfXj"}],"key":"jsohoT1OAr"},{"type":"listItem","spread":true,"position":{"start":{"line":199,"column":1},"end":{"line":200,"column":1}},"children":[{"type":"paragraph","children":[{"type":"strong","position":{"start":{"line":199,"column":1},"end":{"line":199,"column":1}},"children":[{"type":"text","value":"Position Calculations","position":{"start":{"line":199,"column":1},"end":{"line":199,"column":1}},"key":"lu75mKChme"}],"key":"r90a4zEJiM"},{"type":"text","value":": Per-element computations","position":{"start":{"line":199,"column":1},"end":{"line":199,"column":1}},"key":"PDIg8ck1cp"}],"key":"swtkB4DI6S"}],"key":"tHbETVnQZa"}],"key":"fdEtMK1RxL"},{"type":"heading","depth":3,"position":{"start":{"line":201,"column":1},"end":{"line":201,"column":1}},"children":[{"type":"text","value":"Optimization Opportunities","position":{"start":{"line":201,"column":1},"end":{"line":201,"column":1}},"key":"p97nojZmDI"}],"identifier":"optimization-opportunities","label":"Optimization Opportunities","html_id":"optimization-opportunities","implicit":true,"key":"eWSmGP6bCU"},{"type":"list","ordered":true,"start":1,"spread":false,"position":{"start":{"line":202,"column":1},"end":{"line":205,"column":1}},"children":[{"type":"listItem","spread":true,"position":{"start":{"line":202,"column":1},"end":{"line":202,"column":1}},"children":[{"type":"paragraph","children":[{"type":"strong","position":{"start":{"line":202,"column":1},"end":{"line":202,"column":1}},"children":[{"type":"text","value":"Caching","position":{"start":{"line":202,"column":1},"end":{"line":202,"column":1}},"key":"Lof6mQ4HB0"}],"key":"HM4dVIo8QA"},{"type":"text","value":": Cache parsed documents and position calculations","position":{"start":{"line":202,"column":1},"end":{"line":202,"column":1}},"key":"neix7yvSpe"}],"key":"Kg6ZdU39UZ"}],"key":"dzMNLTcxJB"},{"type":"listItem","spread":true,"position":{"start":{"line":203,"column":1},"end":{"line":203,"column":1}},"children":[{"type":"paragraph","children":[{"type":"strong","position":{"start":{"line":203,"column":1},"end":{"line":203,"column":1}},"children":[{"type":"text","value":"Batch Processing","position":{"start":{"line":203,"column":1},"end":{"line":203,"column":1}},"key":"nmaQBwKa0B"}],"key":"u3IOxfvzxq"},{"type":"text","value":": Process multiple images in parallel","position":{"start":{"line":203,"column":1},"end":{"line":203,"column":1}},"key":"tBUcC6NWjm"}],"key":"NNm0fpGOHk"}],"key":"AOzSJcwPUi"},{"type":"listItem","spread":true,"position":{"start":{"line":204,"column":1},"end":{"line":205,"column":1}},"children":[{"type":"paragraph","children":[{"type":"strong","position":{"start":{"line":204,"column":1},"end":{"line":204,"column":1}},"children":[{"type":"text","value":"Lazy Loading","position":{"start":{"line":204,"column":1},"end":{"line":204,"column":1}},"key":"g8uHuRtuce"}],"key":"XrDXyRiKfP"},{"type":"text","value":": Load images only when needed","position":{"start":{"line":204,"column":1},"end":{"line":204,"column":1}},"key":"MxIWDELNoF"}],"key":"WAeBYH71w9"}],"key":"yVG5YrIRL9"}],"key":"fhJeAfoMUb"},{"type":"heading","depth":2,"position":{"start":{"line":206,"column":1},"end":{"line":206,"column":1}},"children":[{"type":"text","value":"Future Enhancements","position":{"start":{"line":206,"column":1},"end":{"line":206,"column":1}},"key":"ARq6djuM9T"}],"identifier":"future-enhancements","label":"Future Enhancements","html_id":"future-enhancements","implicit":true,"key":"Hq2rlQW2FP"},{"type":"heading","depth":3,"position":{"start":{"line":208,"column":1},"end":{"line":208,"column":1}},"children":[{"type":"text","value":"Phase 2: Advanced Features","position":{"start":{"line":208,"column":1},"end":{"line":208,"column":1}},"key":"dvQvcTImWN"}],"identifier":"phase-2-advanced-features","label":"Phase 2: Advanced Features","html_id":"phase-2-advanced-features","implicit":true,"key":"N1mcYSaxCt"},{"type":"list","ordered":false,"spread":false,"position":{"start":{"line":209,"column":1},"end":{"line":213,"column":1}},"children":[{"type":"listItem","spread":true,"position":{"start":{"line":209,"column":1},"end":{"line":209,"column":1}},"children":[{"type":"paragraph","children":[{"type":"strong","position":{"start":{"line":209,"column":1},"end":{"line":209,"column":1}},"children":[{"type":"text","value":"Math Equations","position":{"start":{"line":209,"column":1},"end":{"line":209,"column":1}},"key":"rdBtAxopZ8"}],"key":"XjmzTF2WHM"},{"type":"text","value":": Render LaTeX math as images or text","position":{"start":{"line":209,"column":1},"end":{"line":209,"column":1}},"key":"eBiuRfZ8Wl"}],"key":"hPCu3ULimq"}],"key":"NTLi7MpfMG"},{"type":"listItem","spread":true,"position":{"start":{"line":210,"column":1},"end":{"line":210,"column":1}},"children":[{"type":"paragraph","children":[{"type":"strong","position":{"start":{"line":210,"column":1},"end":{"line":210,"column":1}},"children":[{"type":"text","value":"TikZ Diagrams","position":{"start":{"line":210,"column":1},"end":{"line":210,"column":1}},"key":"WnsBmomhoO"}],"key":"RPgqkumtEU"},{"type":"text","value":": Convert to raster images","position":{"start":{"line":210,"column":1},"end":{"line":210,"column":1}},"key":"qjFgZxaRF3"}],"key":"uBV1JM3OKN"}],"key":"vqsaY8LE2z"},{"type":"listItem","spread":true,"position":{"start":{"line":211,"column":1},"end":{"line":211,"column":1}},"children":[{"type":"paragraph","children":[{"type":"strong","position":{"start":{"line":211,"column":1},"end":{"line":211,"column":1}},"children":[{"type":"text","value":"Custom Commands","position":{"start":{"line":211,"column":1},"end":{"line":211,"column":1}},"key":"zswMCW7xdI"}],"key":"QWa9z4jjCW"},{"type":"text","value":": User-defined LaTeX command support","position":{"start":{"line":211,"column":1},"end":{"line":211,"column":1}},"key":"CiBMZZlRZm"}],"key":"A26IhLXqzC"}],"key":"OxXi9JRsbr"},{"type":"listItem","spread":true,"position":{"start":{"line":212,"column":1},"end":{"line":213,"column":1}},"children":[{"type":"paragraph","children":[{"type":"strong","position":{"start":{"line":212,"column":1},"end":{"line":212,"column":1}},"children":[{"type":"text","value":"Overlays","position":{"start":{"line":212,"column":1},"end":{"line":212,"column":1}},"key":"MC2d2mPKrj"}],"key":"T1omDFdUCn"},{"type":"text","value":": Handle Beamer overlay specifications","position":{"start":{"line":212,"column":1},"end":{"line":212,"column":1}},"key":"VwVWPKn9Ag"}],"key":"BDD2iODboS"}],"key":"ggGj7ToVLB"}],"key":"VMbjmF52RH"},{"type":"heading","depth":3,"position":{"start":{"line":214,"column":1},"end":{"line":214,"column":1}},"children":[{"type":"text","value":"Phase 3: Multi-Format Support","position":{"start":{"line":214,"column":1},"end":{"line":214,"column":1}},"key":"IP8dmS6a23"}],"identifier":"phase-3-multi-format-support","label":"Phase 3: Multi-Format Support","html_id":"phase-3-multi-format-support","implicit":true,"key":"BIHtklIsDM"},{"type":"list","ordered":false,"spread":false,"position":{"start":{"line":215,"column":1},"end":{"line":218,"column":1}},"children":[{"type":"listItem","spread":true,"position":{"start":{"line":215,"column":1},"end":{"line":215,"column":1}},"children":[{"type":"paragraph","children":[{"type":"strong","position":{"start":{"line":215,"column":1},"end":{"line":215,"column":1}},"children":[{"type":"text","value":"PowerPoint → LaTeX","position":{"start":{"line":215,"column":1},"end":{"line":215,"column":1}},"key":"P60uBV7rGB"}],"key":"Zyo2cQboHx"},{"type":"text","value":": Round-trip conversion","position":{"start":{"line":215,"column":1},"end":{"line":215,"column":1}},"key":"ZZeAhq8cM0"}],"key":"NA9wwJa24r"}],"key":"iWIG5RoaOO"},{"type":"listItem","spread":true,"position":{"start":{"line":216,"column":1},"end":{"line":216,"column":1}},"children":[{"type":"paragraph","children":[{"type":"strong","position":{"start":{"line":216,"column":1},"end":{"line":216,"column":1}},"children":[{"type":"text","value":"Markdown Support","position":{"start":{"line":216,"column":1},"end":{"line":216,"column":1}},"key":"v9LLKzGk26"}],"key":"UdLaMjBlz4"},{"type":"text","value":": MD to PowerPoint conversion","position":{"start":{"line":216,"column":1},"end":{"line":216,"column":1}},"key":"nnsRCeeXy7"}],"key":"rWswO4DLN3"}],"key":"hV2NFmyUp0"},{"type":"listItem","spread":true,"position":{"start":{"line":217,"column":1},"end":{"line":218,"column":1}},"children":[{"type":"paragraph","children":[{"type":"strong","position":{"start":{"line":217,"column":1},"end":{"line":217,"column":1}},"children":[{"type":"text","value":"HTML Export","position":{"start":{"line":217,"column":1},"end":{"line":217,"column":1}},"key":"xaYJIS1sNP"}],"key":"iIq8hgjaEd"},{"type":"text","value":": Web-based presentation formats","position":{"start":{"line":217,"column":1},"end":{"line":217,"column":1}},"key":"uwgA6CfcBd"}],"key":"qzC7EpeCTo"}],"key":"yAasB1eNzs"}],"key":"kHCtoRf1cs"},{"type":"heading","depth":3,"position":{"start":{"line":219,"column":1},"end":{"line":219,"column":1}},"children":[{"type":"text","value":"Phase 4: Advanced Features","position":{"start":{"line":219,"column":1},"end":{"line":219,"column":1}},"key":"IWWgcPJGmA"}],"identifier":"phase-4-advanced-features","label":"Phase 4: Advanced Features","html_id":"phase-4-advanced-features","implicit":true,"key":"Yhiyz0e56O"},{"type":"list","ordered":false,"spread":false,"position":{"start":{"line":220,"column":1},"end":{"line":223,"column":1}},"children":[{"type":"listItem","spread":true,"position":{"start":{"line":220,"column":1},"end":{"line":220,"column":1}},"children":[{"type":"paragraph","children":[{"type":"strong","position":{"start":{"line":220,"column":1},"end":{"line":220,"column":1}},"children":[{"type":"text","value":"Template System","position":{"start":{"line":220,"column":1},"end":{"line":220,"column":1}},"key":"MEMHNHsSoJ"}],"key":"JEdjvYAMqp"},{"type":"text","value":": Custom PowerPoint templates","position":{"start":{"line":220,"column":1},"end":{"line":220,"column":1}},"key":"LoRczCMqK7"}],"key":"VnU9g1AXir"}],"key":"oMBMFuQdNq"},{"type":"listItem","spread":true,"position":{"start":{"line":221,"column":1},"end":{"line":221,"column":1}},"children":[{"type":"paragraph","children":[{"type":"strong","position":{"start":{"line":221,"column":1},"end":{"line":221,"column":1}},"children":[{"type":"text","value":"Animation Support","position":{"start":{"line":221,"column":1},"end":{"line":221,"column":1}},"key":"OWEwHJQptc"}],"key":"rrhpJaT5ld"},{"type":"text","value":": PowerPoint animations from LaTeX overlays","position":{"start":{"line":221,"column":1},"end":{"line":221,"column":1}},"key":"uG6Biwjz5s"}],"key":"SKj2VPtZyz"}],"key":"mLGuz0bX5d"},{"type":"listItem","spread":true,"position":{"start":{"line":222,"column":1},"end":{"line":223,"column":1}},"children":[{"type":"paragraph","children":[{"type":"strong","position":{"start":{"line":222,"column":1},"end":{"line":222,"column":1}},"children":[{"type":"text","value":"Plugin Architecture","position":{"start":{"line":222,"column":1},"end":{"line":222,"column":1}},"key":"fWOfT5Kt3m"}],"key":"XXSnG4Qymq"},{"type":"text","value":": Extensible parser/builder system","position":{"start":{"line":222,"column":1},"end":{"line":222,"column":1}},"key":"a54Lr6cRVj"}],"key":"u1Rvxbj4Qq"}],"key":"rB70lsML0z"}],"key":"yvhXRETNSm"},{"type":"heading","depth":2,"position":{"start":{"line":224,"column":1},"end":{"line":224,"column":1}},"children":[{"type":"text","value":"Testing Strategy","position":{"start":{"line":224,"column":1},"end":{"line":224,"column":1}},"key":"qWM5pRSfFh"}],"identifier":"testing-strategy","label":"Testing Strategy","html_id":"testing-strategy","implicit":true,"key":"d6a51d4dF6"},{"type":"heading","depth":3,"position":{"start":{"line":226,"column":1},"end":{"line":226,"column":1}},"children":[{"type":"text","value":"Current Testing Gaps","position":{"start":{"line":226,"column":1},"end":{"line":226,"column":1}},"key":"BVSBKYDhJo"}],"identifier":"current-testing-gaps","label":"Current Testing Gaps","html_id":"current-testing-gaps","implicit":true,"key":"KKKukxazxy"},{"type":"list","ordered":true,"start":1,"spread":false,"position":{"start":{"line":227,"column":1},"end":{"line":230,"column":1}},"children":[{"type":"listItem","spread":true,"position":{"start":{"line":227,"column":1},"end":{"line":227,"column":1}},"children":[{"type":"paragraph","children":[{"type":"strong","position":{"start":{"line":227,"column":1},"end":{"line":227,"column":1}},"children":[{"type":"text","value":"Integration Tests","position":{"start":{"line":227,"column":1},"end":{"line":227,"column":1}},"key":"cMuKOtby5S"}],"key":"tlzENxNzNc"},{"type":"text","value":": End-to-end conversion testing","position":{"start":{"line":227,"column":1},"end":{"line":227,"column":1}},"key":"ECiRiJneuE"}],"key":"tRILqnJ17V"}],"key":"zJFYwRXxbw"},{"type":"listItem","spread":true,"position":{"start":{"line":228,"column":1},"end":{"line":228,"column":1}},"children":[{"type":"paragraph","children":[{"type":"strong","position":{"start":{"line":228,"column":1},"end":{"line":228,"column":1}},"children":[{"type":"text","value":"Edge Cases","position":{"start":{"line":228,"column":1},"end":{"line":228,"column":1}},"key":"IIjA7Hm0D0"}],"key":"yxp6uEPkXY"},{"type":"text","value":": Complex LaTeX structures","position":{"start":{"line":228,"column":1},"end":{"line":228,"column":1}},"key":"m1LZapixtW"}],"key":"YrermbkGyk"}],"key":"XfimcPZquC"},{"type":"listItem","spread":true,"position":{"start":{"line":229,"column":1},"end":{"line":230,"column":1}},"children":[{"type":"paragraph","children":[{"type":"strong","position":{"start":{"line":229,"column":1},"end":{"line":229,"column":1}},"children":[{"type":"text","value":"Performance Tests","position":{"start":{"line":229,"column":1},"end":{"line":229,"column":1}},"key":"Tiok1x3HEG"}],"key":"nrpZuDHT2c"},{"type":"text","value":": Large presentation handling","position":{"start":{"line":229,"column":1},"end":{"line":229,"column":1}},"key":"Mfm30jZmTB"}],"key":"aYvwQhxKXg"}],"key":"XhMTFaG1Db"}],"key":"lJWq9tgRGX"},{"type":"heading","depth":3,"position":{"start":{"line":231,"column":1},"end":{"line":231,"column":1}},"children":[{"type":"text","value":"Recommended Test Structure","position":{"start":{"line":231,"column":1},"end":{"line":231,"column":1}},"key":"HUSJDkzpTv"}],"identifier":"recommended-test-structure","label":"Recommended Test Structure","html_id":"recommended-test-structure","implicit":true,"key":"QJVoJqsgdD"},{"type":"code","lang":"","value":"tests/\n├── unit/\n│   ├── test_parser.py\n│   ├── test_mapper.py\n│   └── test_builder.py\n├── integration/\n│   ├── test_simple_conversion.py\n│   ├── test_complex_conversion.py\n│   └── test_error_handling.py\n├── fixtures/\n│   ├── latex/\n│   └── expected/\n└── performance/\n    └── test_large_files.py","position":{"start":{"line":232,"column":1},"end":{"line":247,"column":1}},"key":"mIFj9AyGKH"},{"type":"heading","depth":2,"position":{"start":{"line":249,"column":1},"end":{"line":249,"column":1}},"children":[{"type":"text","value":"Conclusion","position":{"start":{"line":249,"column":1},"end":{"line":249,"column":1}},"key":"CvZdx0qmN0"}],"identifier":"conclusion","label":"Conclusion","html_id":"conclusion","implicit":true,"key":"C3lNr1je2n"},{"type":"paragraph","position":{"start":{"line":251,"column":1},"end":{"line":251,"column":1}},"children":[{"type":"text","value":"The current architecture has proven effective for basic LaTeX to PowerPoint conversion. The key success factors are:","position":{"start":{"line":251,"column":1},"end":{"line":251,"column":1}},"key":"m7E0huELUg"}],"key":"DG8y93cpFi"},{"type":"list","ordered":true,"start":1,"spread":false,"position":{"start":{"line":253,"column":1},"end":{"line":258,"column":1}},"children":[{"type":"listItem","spread":true,"position":{"start":{"line":253,"column":1},"end":{"line":253,"column":1}},"children":[{"type":"paragraph","children":[{"type":"strong","position":{"start":{"line":253,"column":1},"end":{"line":253,"column":1}},"children":[{"type":"text","value":"Clean Separation","position":{"start":{"line":253,"column":1},"end":{"line":253,"column":1}},"key":"g94717v3iH"}],"key":"r0JRzyouC3"},{"type":"text","value":": Parser → Mapper → Builder pipeline","position":{"start":{"line":253,"column":1},"end":{"line":253,"column":1}},"key":"d6H1YAy4NB"}],"key":"u2fbEfAbSU"}],"key":"UJOsE6MP1e"},{"type":"listItem","spread":true,"position":{"start":{"line":254,"column":1},"end":{"line":254,"column":1}},"children":[{"type":"paragraph","children":[{"type":"strong","position":{"start":{"line":254,"column":1},"end":{"line":254,"column":1}},"children":[{"type":"text","value":"Universal Models","position":{"start":{"line":254,"column":1},"end":{"line":254,"column":1}},"key":"qgwF5rxFTC"}],"key":"tl0ILrNFjA"},{"type":"text","value":": Format-agnostic data structures","position":{"start":{"line":254,"column":1},"end":{"line":254,"column":1}},"key":"QbZ3mVuoaz"}],"key":"FvCmiFVAde"}],"key":"SCV0G4lKOm"},{"type":"listItem","spread":true,"position":{"start":{"line":255,"column":1},"end":{"line":255,"column":1}},"children":[{"type":"paragraph","children":[{"type":"strong","position":{"start":{"line":255,"column":1},"end":{"line":255,"column":1}},"children":[{"type":"text","value":"Smart Positioning","position":{"start":{"line":255,"column":1},"end":{"line":255,"column":1}},"key":"AdDFxed0mB"}],"key":"mvLDexkCwr"},{"type":"text","value":": Layout-aware content placement","position":{"start":{"line":255,"column":1},"end":{"line":255,"column":1}},"key":"RFIWdcObON"}],"key":"IA4CIlZURx"}],"key":"hWTW71jM7Q"},{"type":"listItem","spread":true,"position":{"start":{"line":256,"column":1},"end":{"line":256,"column":1}},"children":[{"type":"paragraph","children":[{"type":"strong","position":{"start":{"line":256,"column":1},"end":{"line":256,"column":1}},"children":[{"type":"text","value":"Native Integration","position":{"start":{"line":256,"column":1},"end":{"line":256,"column":1}},"key":"azTkHtTKyO"}],"key":"L9uxsOZXvJ"},{"type":"text","value":": Respect for PowerPoint’s structure","position":{"start":{"line":256,"column":1},"end":{"line":256,"column":1}},"key":"g8gDxDmKVz"}],"key":"m6RAFXPg4C"}],"key":"wCciaZdB73"},{"type":"listItem","spread":true,"position":{"start":{"line":257,"column":1},"end":{"line":258,"column":1}},"children":[{"type":"paragraph","children":[{"type":"strong","position":{"start":{"line":257,"column":1},"end":{"line":257,"column":1}},"children":[{"type":"text","value":"Robust Error Handling","position":{"start":{"line":257,"column":1},"end":{"line":257,"column":1}},"key":"dMykvSo2F6"}],"key":"HpXRAAtnox"},{"type":"text","value":": Graceful degradation when things go wrong","position":{"start":{"line":257,"column":1},"end":{"line":257,"column":1}},"key":"r1h6VeSAOR"}],"key":"pxrhoyaGIs"}],"key":"kYfGVaNYUW"}],"key":"dnIjgj7JxU"},{"type":"paragraph","position":{"start":{"line":259,"column":1},"end":{"line":259,"column":1}},"children":[{"type":"text","value":"The system is now ready for Phase 2 enhancements while maintaining the solid foundation established in Phase 1.","position":{"start":{"line":259,"column":1},"end":{"line":259,"column":1}},"key":"sCUUw0iHTf"}],"key":"tfUEYLTI7k"}],"key":"u71EIh28RB"}],"key":"tWIYUduXBP"},"references":{"cite":{"order":[],"data":{}}},"footer":{"navigation":{"prev":{"title":"Sequence Diagrams","url":"/sequence-diagrams","group":"Reference"}}},"domain":"http://localhost:3000"}