{"version":3,"kind":"Article","sha256":"3b0ab440fa5ba00eaa3a3d2e509a15a6c514826d1344b5942188b365acee8d7a","slug":"intro","location":"/intro.md","dependencies":[],"frontmatter":{"title":"Slide Forge Documentation","content_includes_title":false,"authors":[{"nameParsed":{"literal":"Slide Forge Team","given":"Slide Forge","family":"Team"},"name":"Slide Forge Team","id":"contributors-myst-generated-uid-0"}],"github":"https://github.com/marvins/slide-forge","keywords":["latex","beamer","powerpoint","conversion","python"],"source_url":"https://github.com/marvins/slide-forge/blob/main/docs/book/intro.md","edit_url":"https://github.com/marvins/slide-forge/edit/main/docs/book/intro.md","exports":[{"format":"md","filename":"intro.md","url":"/build/intro-e0e52da09100e800f79a7ef9652d29cc.md"}]},"mdast":{"type":"root","children":[{"type":"block","children":[{"type":"paragraph","position":{"start":{"line":3,"column":1},"end":{"line":3,"column":1}},"children":[{"type":"text","value":"Welcome to the official documentation for ","position":{"start":{"line":3,"column":1},"end":{"line":3,"column":1}},"key":"ixmyEcblrL"},{"type":"strong","position":{"start":{"line":3,"column":1},"end":{"line":3,"column":1}},"children":[{"type":"text","value":"Slide Forge","position":{"start":{"line":3,"column":1},"end":{"line":3,"column":1}},"key":"a3l98nnnYo"}],"key":"gUIouI95WO"},{"type":"text","value":" - a powerful tool that converts LaTeX Beamer presentations into professional PowerPoint slides.","position":{"start":{"line":3,"column":1},"end":{"line":3,"column":1}},"key":"SWhzNxI6EH"}],"key":"QOArFjdjCc"},{"type":"heading","depth":2,"position":{"start":{"line":5,"column":1},"end":{"line":5,"column":1}},"children":[{"type":"text","value":"What is Slide Forge?","position":{"start":{"line":5,"column":1},"end":{"line":5,"column":1}},"key":"qsGYt7hhUY"}],"identifier":"what-is-slide-forge","label":"What is Slide Forge?","html_id":"what-is-slide-forge","implicit":true,"key":"ed2KISlq40"},{"type":"paragraph","position":{"start":{"line":7,"column":1},"end":{"line":7,"column":1}},"children":[{"type":"text","value":"Slide Forge is a Python library and command-line tool that transforms academic presentations from LaTeX Beamer format to PowerPoint (.pptx) format. It preserves the structure, styling, and content of your presentations while making them accessible in Microsoft PowerPoint.","position":{"start":{"line":7,"column":1},"end":{"line":7,"column":1}},"key":"kqpNE7CZja"}],"key":"rZbZy1Ho7f"},{"type":"heading","depth":2,"position":{"start":{"line":9,"column":1},"end":{"line":9,"column":1}},"children":[{"type":"text","value":"Key Features","position":{"start":{"line":9,"column":1},"end":{"line":9,"column":1}},"key":"zUXr7DYPPY"}],"identifier":"key-features","label":"Key Features","html_id":"key-features","implicit":true,"key":"UsQGGJl0Yc"},{"type":"list","ordered":false,"spread":false,"position":{"start":{"line":11,"column":1},"end":{"line":17,"column":1}},"children":[{"type":"listItem","spread":true,"position":{"start":{"line":11,"column":1},"end":{"line":11,"column":1}},"children":[{"type":"paragraph","children":[{"type":"text","value":"🎯 ","position":{"start":{"line":11,"column":1},"end":{"line":11,"column":1}},"key":"qgeupH2QjG"},{"type":"strong","position":{"start":{"line":11,"column":1},"end":{"line":11,"column":1}},"children":[{"type":"text","value":"Accurate Conversion","position":{"start":{"line":11,"column":1},"end":{"line":11,"column":1}},"key":"JtwR9TxiNf"}],"key":"XcwoGMa5ij"},{"type":"text","value":" - Maintains slide structure, titles, and content organization","position":{"start":{"line":11,"column":1},"end":{"line":11,"column":1}},"key":"NFaTnqy1Mx"}],"key":"xybIGG2tVc"}],"key":"h61wPoBPRh"},{"type":"listItem","spread":true,"position":{"start":{"line":12,"column":1},"end":{"line":12,"column":1}},"children":[{"type":"paragraph","children":[{"type":"text","value":"🎨 ","position":{"start":{"line":12,"column":1},"end":{"line":12,"column":1}},"key":"GErFJzYTUu"},{"type":"strong","position":{"start":{"line":12,"column":1},"end":{"line":12,"column":1}},"children":[{"type":"text","value":"Style Preservation","position":{"start":{"line":12,"column":1},"end":{"line":12,"column":1}},"key":"g5JiVO6pzG"}],"key":"vq9Co97QCD"},{"type":"text","value":" - Preserves LaTeX styling and formatting in PowerPoint","position":{"start":{"line":12,"column":1},"end":{"line":12,"column":1}},"key":"cwRjqchBv5"}],"key":"IABP0prSuz"}],"key":"NksGKRyc7U"},{"type":"listItem","spread":true,"position":{"start":{"line":13,"column":1},"end":{"line":13,"column":1}},"children":[{"type":"paragraph","children":[{"type":"text","value":"🖼️ ","position":{"start":{"line":13,"column":1},"end":{"line":13,"column":1}},"key":"NOPuQHuuVc"},{"type":"strong","position":{"start":{"line":13,"column":1},"end":{"line":13,"column":1}},"children":[{"type":"text","value":"Image Support","position":{"start":{"line":13,"column":1},"end":{"line":13,"column":1}},"key":"sXFGJG8A9x"}],"key":"zrvDHrwjpT"},{"type":"text","value":" - Extracts and includes images from LaTeX presentations","position":{"start":{"line":13,"column":1},"end":{"line":13,"column":1}},"key":"brPbTl5OZc"}],"key":"Be9SW5Z1KM"}],"key":"zc4XqIAtl8"},{"type":"listItem","spread":true,"position":{"start":{"line":14,"column":1},"end":{"line":14,"column":1}},"children":[{"type":"paragraph","children":[{"type":"text","value":"🔧 ","position":{"start":{"line":14,"column":1},"end":{"line":14,"column":1}},"key":"ZXULzZfj1a"},{"type":"strong","position":{"start":{"line":14,"column":1},"end":{"line":14,"column":1}},"children":[{"type":"text","value":"Flexible Options","position":{"start":{"line":14,"column":1},"end":{"line":14,"column":1}},"key":"G7vqXoWCaI"}],"key":"jrs3gmUGq3"},{"type":"text","value":" - Multiple themes and customization options","position":{"start":{"line":14,"column":1},"end":{"line":14,"column":1}},"key":"ZibBbjNssN"}],"key":"cLBpZCeqB9"}],"key":"v4vXGbpuh8"},{"type":"listItem","spread":true,"position":{"start":{"line":15,"column":1},"end":{"line":15,"column":1}},"children":[{"type":"paragraph","children":[{"type":"text","value":"📚 ","position":{"start":{"line":15,"column":1},"end":{"line":15,"column":1}},"key":"f1D8Pe0oAO"},{"type":"strong","position":{"start":{"line":15,"column":1},"end":{"line":15,"column":1}},"children":[{"type":"text","value":"Easy Integration","position":{"start":{"line":15,"column":1},"end":{"line":15,"column":1}},"key":"ZyiwlIbVFX"}],"key":"HLgynbXE3B"},{"type":"text","value":" - Both CLI tool and Python library","position":{"start":{"line":15,"column":1},"end":{"line":15,"column":1}},"key":"WsoVhn9m3i"}],"key":"OXvjctxkji"}],"key":"G1NyCfQhL7"},{"type":"listItem","spread":true,"position":{"start":{"line":16,"column":1},"end":{"line":17,"column":1}},"children":[{"type":"paragraph","children":[{"type":"text","value":"🚀 ","position":{"start":{"line":16,"column":1},"end":{"line":16,"column":1}},"key":"t7Zisdc36a"},{"type":"strong","position":{"start":{"line":16,"column":1},"end":{"line":16,"column":1}},"children":[{"type":"text","value":"Fast Processing","position":{"start":{"line":16,"column":1},"end":{"line":16,"column":1}},"key":"Y8fqvRd6It"}],"key":"SbFNApIM8l"},{"type":"text","value":" - Efficient conversion workflow","position":{"start":{"line":16,"column":1},"end":{"line":16,"column":1}},"key":"EP8CWXFbNv"}],"key":"jofuS8JkGk"}],"key":"q23sEVvUeW"}],"key":"qYKDrHvN2l"},{"type":"heading","depth":2,"position":{"start":{"line":18,"column":1},"end":{"line":18,"column":1}},"children":[{"type":"text","value":"Who is this for?","position":{"start":{"line":18,"column":1},"end":{"line":18,"column":1}},"key":"dZdPUYLDsO"}],"identifier":"who-is-this-for","label":"Who is this for?","html_id":"who-is-this-for","implicit":true,"key":"E269aQIZtW"},{"type":"list","ordered":false,"spread":false,"position":{"start":{"line":20,"column":1},"end":{"line":24,"column":1}},"children":[{"type":"listItem","spread":true,"position":{"start":{"line":20,"column":1},"end":{"line":20,"column":1}},"children":[{"type":"paragraph","children":[{"type":"strong","position":{"start":{"line":20,"column":1},"end":{"line":20,"column":1}},"children":[{"type":"text","value":"Academics","position":{"start":{"line":20,"column":1},"end":{"line":20,"column":1}},"key":"Kf3odTYqoW"}],"key":"K6QUNVIEvV"},{"type":"text","value":" who need to share LaTeX presentations with colleagues using PowerPoint","position":{"start":{"line":20,"column":1},"end":{"line":20,"column":1}},"key":"gNwibXYmHf"}],"key":"i73mrPNOjV"}],"key":"o9121QoZUS"},{"type":"listItem","spread":true,"position":{"start":{"line":21,"column":1},"end":{"line":21,"column":1}},"children":[{"type":"paragraph","children":[{"type":"strong","position":{"start":{"line":21,"column":1},"end":{"line":21,"column":1}},"children":[{"type":"text","value":"Students","position":{"start":{"line":21,"column":1},"end":{"line":21,"column":1}},"key":"rh4a6pb1Dx"}],"key":"ySE8OLz13C"},{"type":"text","value":" converting thesis presentations for job talks","position":{"start":{"line":21,"column":1},"end":{"line":21,"column":1}},"key":"yquEeZ0jN7"}],"key":"cyzCkKp4kt"}],"key":"msyp6KrS9C"},{"type":"listItem","spread":true,"position":{"start":{"line":22,"column":1},"end":{"line":22,"column":1}},"children":[{"type":"paragraph","children":[{"type":"strong","position":{"start":{"line":22,"column":1},"end":{"line":22,"column":1}},"children":[{"type":"text","value":"Researchers","position":{"start":{"line":22,"column":1},"end":{"line":22,"column":1}},"key":"hgRY7OMBpp"}],"key":"exJkgkKI6t"},{"type":"text","value":" preparing conference presentations","position":{"start":{"line":22,"column":1},"end":{"line":22,"column":1}},"key":"fXq0xczeBI"}],"key":"XwmXtJqu7S"}],"key":"KlRF15ecEZ"},{"type":"listItem","spread":true,"position":{"start":{"line":23,"column":1},"end":{"line":24,"column":1}},"children":[{"type":"paragraph","children":[{"type":"strong","position":{"start":{"line":23,"column":1},"end":{"line":23,"column":1}},"children":[{"type":"text","value":"Anyone","position":{"start":{"line":23,"column":1},"end":{"line":23,"column":1}},"key":"xpd7m5pT6J"}],"key":"YpCRogAIBe"},{"type":"text","value":" needing to bridge the LaTeX-PowerPoint gap","position":{"start":{"line":23,"column":1},"end":{"line":23,"column":1}},"key":"ueNCtM4r6r"}],"key":"I0qrlQTPZ2"}],"key":"ImUlDwoTBk"}],"key":"XyTtdZrRmC"},{"type":"heading","depth":2,"position":{"start":{"line":25,"column":1},"end":{"line":25,"column":1}},"children":[{"type":"text","value":"How to Use This Documentation","position":{"start":{"line":25,"column":1},"end":{"line":25,"column":1}},"key":"mJN7oDhyZy"}],"identifier":"how-to-use-this-documentation","label":"How to Use This Documentation","html_id":"how-to-use-this-documentation","implicit":true,"key":"VWh1GcAJs5"},{"type":"heading","depth":3,"position":{"start":{"line":27,"column":1},"end":{"line":27,"column":1}},"children":[{"type":"text","value":"📖 ","position":{"start":{"line":27,"column":1},"end":{"line":27,"column":1}},"key":"KsNwe12DAN"},{"type":"strong","position":{"start":{"line":27,"column":1},"end":{"line":27,"column":1}},"children":[{"type":"text","value":"Reading Path","position":{"start":{"line":27,"column":1},"end":{"line":27,"column":1}},"key":"ksqaBuNRoL"}],"key":"zJPurtgM47"}],"identifier":"id-reading-path","label":"📖 Reading Path","html_id":"id-reading-path","implicit":true,"key":"dxTMdZDF8P"},{"type":"list","ordered":true,"start":1,"spread":false,"position":{"start":{"line":28,"column":1},"end":{"line":32,"column":1}},"children":[{"type":"listItem","spread":true,"position":{"start":{"line":28,"column":1},"end":{"line":28,"column":1}},"children":[{"type":"paragraph","children":[{"type":"strong","position":{"start":{"line":28,"column":1},"end":{"line":28,"column":1}},"children":[{"type":"text","value":"New Users","position":{"start":{"line":28,"column":1},"end":{"line":28,"column":1}},"key":"KNu9ItOMAi"}],"key":"vvvmxu1rRa"},{"type":"text","value":" → Start with ","position":{"start":{"line":28,"column":1},"end":{"line":28,"column":1}},"key":"IvLTGz4NdQ"},{"type":"link","url":"getting-started.md","position":{"start":{"line":28,"column":1},"end":{"line":28,"column":1}},"children":[{"type":"text","value":"Getting Started","position":{"start":{"line":28,"column":1},"end":{"line":28,"column":1}},"key":"OLTScCS93u"}],"urlSource":"getting-started.md","key":"Us9AFvE4s9"}],"key":"H3KQDpMMhE"}],"key":"rRsotWYJA6"},{"type":"listItem","spread":true,"position":{"start":{"line":29,"column":1},"end":{"line":29,"column":1}},"children":[{"type":"paragraph","children":[{"type":"strong","position":{"start":{"line":29,"column":1},"end":{"line":29,"column":1}},"children":[{"type":"text","value":"Quick Start","position":{"start":{"line":29,"column":1},"end":{"line":29,"column":1}},"key":"glyPQNEvxN"}],"key":"OyBmA6O69x"},{"type":"text","value":" → Jump to ","position":{"start":{"line":29,"column":1},"end":{"line":29,"column":1}},"key":"BZSGKVoMkv"},{"type":"link","url":"/quickstart","position":{"start":{"line":29,"column":1},"end":{"line":29,"column":1}},"children":[{"type":"text","value":"Quick Start Guide","position":{"start":{"line":29,"column":1},"end":{"line":29,"column":1}},"key":"IQc4dxNmfC"}],"urlSource":"quickstart.md","dataUrl":"/quickstart.json","internal":true,"protocol":"file","key":"UWUDDAxmKX"}],"key":"QKIUHzIjyj"}],"key":"UeyyQMJRtH"},{"type":"listItem","spread":true,"position":{"start":{"line":30,"column":1},"end":{"line":30,"column":1}},"children":[{"type":"paragraph","children":[{"type":"strong","position":{"start":{"line":30,"column":1},"end":{"line":30,"column":1}},"children":[{"type":"text","value":"Developers","position":{"start":{"line":30,"column":1},"end":{"line":30,"column":1}},"key":"LW1WBXmgD6"}],"key":"uO2dnt6G7F"},{"type":"text","value":" → Check the ","position":{"start":{"line":30,"column":1},"end":{"line":30,"column":1}},"key":"ReewL3LPZ5"},{"type":"link","url":"api/","position":{"start":{"line":30,"column":1},"end":{"line":30,"column":1}},"children":[{"type":"text","value":"API Reference","position":{"start":{"line":30,"column":1},"end":{"line":30,"column":1}},"key":"nYrsCCme3T"}],"urlSource":"api/","key":"QpksLV8MvN"}],"key":"mefXckmJFj"}],"key":"y0H4IQ1F3H"},{"type":"listItem","spread":true,"position":{"start":{"line":31,"column":1},"end":{"line":32,"column":1}},"children":[{"type":"paragraph","children":[{"type":"strong","position":{"start":{"line":31,"column":1},"end":{"line":31,"column":1}},"children":[{"type":"text","value":"Examples","position":{"start":{"line":31,"column":1},"end":{"line":31,"column":1}},"key":"PjfJfAnk4U"}],"key":"PJBMoR1T2F"},{"type":"text","value":" → Browse ","position":{"start":{"line":31,"column":1},"end":{"line":31,"column":1}},"key":"Sx7v9HD2hV"},{"type":"link","url":"examples/","position":{"start":{"line":31,"column":1},"end":{"line":31,"column":1}},"children":[{"type":"text","value":"Examples","position":{"start":{"line":31,"column":1},"end":{"line":31,"column":1}},"key":"vuVz6DwYvt"}],"urlSource":"examples/","key":"bBhhr84IaF"},{"type":"text","value":" for real-world usage","position":{"start":{"line":31,"column":1},"end":{"line":31,"column":1}},"key":"GeteXyHqgc"}],"key":"vdsBHqIeir"}],"key":"dRwUFhOfPd"}],"key":"ncHGgTjv1W"},{"type":"heading","depth":3,"position":{"start":{"line":33,"column":1},"end":{"line":33,"column":1}},"children":[{"type":"text","value":"🔧 ","position":{"start":{"line":33,"column":1},"end":{"line":33,"column":1}},"key":"zhD1A8VdMB"},{"type":"strong","position":{"start":{"line":33,"column":1},"end":{"line":33,"column":1}},"children":[{"type":"text","value":"Interactive Tutorials","position":{"start":{"line":33,"column":1},"end":{"line":33,"column":1}},"key":"aa3vp7eNFo"}],"key":"UIGqKSzYI0"}],"identifier":"id-interactive-tutorials","label":"🔧 Interactive Tutorials","html_id":"id-interactive-tutorials","implicit":true,"key":"ds1eJEZYFE"},{"type":"paragraph","position":{"start":{"line":34,"column":1},"end":{"line":34,"column":1}},"children":[{"type":"text","value":"Our tutorial notebooks include executable code cells that you can run directly in your browser or local environment. Look for the 📚 icon to identify interactive content.","position":{"start":{"line":34,"column":1},"end":{"line":34,"column":1}},"key":"gIMvuEiDvf"}],"key":"vIdp90vYVR"},{"type":"heading","depth":3,"position":{"start":{"line":36,"column":1},"end":{"line":36,"column":1}},"children":[{"type":"text","value":"📚 ","position":{"start":{"line":36,"column":1},"end":{"line":36,"column":1}},"key":"XKK1r2wNol"},{"type":"strong","position":{"start":{"line":36,"column":1},"end":{"line":36,"column":1}},"children":[{"type":"text","value":"Navigation","position":{"start":{"line":36,"column":1},"end":{"line":36,"column":1}},"key":"ODAGoRbgpy"}],"key":"X9qPIleNPP"}],"identifier":"id-navigation","label":"📚 Navigation","html_id":"id-navigation","implicit":true,"key":"Q8BuUA3Ojr"},{"type":"list","ordered":false,"spread":false,"position":{"start":{"line":37,"column":1},"end":{"line":40,"column":1}},"children":[{"type":"listItem","spread":true,"position":{"start":{"line":37,"column":1},"end":{"line":37,"column":1}},"children":[{"type":"paragraph","children":[{"type":"text","value":"Use the table of contents on the left to navigate between sections","position":{"start":{"line":37,"column":1},"end":{"line":37,"column":1}},"key":"VjoNUnZplq"}],"key":"v4Njm5KKLa"}],"key":"kK9cFqat1O"},{"type":"listItem","spread":true,"position":{"start":{"line":38,"column":1},"end":{"line":38,"column":1}},"children":[{"type":"paragraph","children":[{"type":"text","value":"Search functionality helps you find specific topics quickly","position":{"start":{"line":38,"column":1},"end":{"line":38,"column":1}},"key":"GAvu5rxTah"}],"key":"HTSEerGJag"}],"key":"weXTkzidIr"},{"type":"listItem","spread":true,"position":{"start":{"line":39,"column":1},"end":{"line":40,"column":1}},"children":[{"type":"paragraph","children":[{"type":"text","value":"Cross-references link related concepts throughout the documentation","position":{"start":{"line":39,"column":1},"end":{"line":39,"column":1}},"key":"F5YGgXz35v"}],"key":"Yv98oAmSwz"}],"key":"e7hz3XB4G8"}],"key":"AQobpHD0ZX"},{"type":"heading","depth":2,"position":{"start":{"line":41,"column":1},"end":{"line":41,"column":1}},"children":[{"type":"text","value":"Quick Example","position":{"start":{"line":41,"column":1},"end":{"line":41,"column":1}},"key":"uIb4ddZuz7"}],"identifier":"quick-example","label":"Quick Example","html_id":"quick-example","implicit":true,"key":"Z8KFTPFz1T"},{"type":"code","lang":"python","value":"from slideforge import Slide_Forge\n\n# Initialize the converter\nconverter = Slide_Forge()\n\n# Convert a LaTeX Beamer presentation\nsuccess = converter.convert_file(\n    \"presentation.tex\", \n    \"presentation.pptx\",\n    theme=\"professional\",\n    preserve_colors=True\n)\n\nif success:\n    print(\"Conversion successful!\")","position":{"start":{"line":43,"column":1},"end":{"line":59,"column":1}},"key":"H00IXRSqMF"},{"type":"heading","depth":2,"position":{"start":{"line":61,"column":1},"end":{"line":61,"column":1}},"children":[{"type":"text","value":"Getting Help","position":{"start":{"line":61,"column":1},"end":{"line":61,"column":1}},"key":"Sfs4pdCXpF"}],"identifier":"getting-help","label":"Getting Help","html_id":"getting-help","implicit":true,"key":"fc5G2LBtf4"},{"type":"list","ordered":false,"spread":false,"position":{"start":{"line":63,"column":1},"end":{"line":67,"column":1}},"children":[{"type":"listItem","spread":true,"position":{"start":{"line":63,"column":1},"end":{"line":63,"column":1}},"children":[{"type":"paragraph","children":[{"type":"text","value":"📖 ","position":{"start":{"line":63,"column":1},"end":{"line":63,"column":1}},"key":"mPSlKwicAX"},{"type":"strong","position":{"start":{"line":63,"column":1},"end":{"line":63,"column":1}},"children":[{"type":"text","value":"Documentation","position":{"start":{"line":63,"column":1},"end":{"line":63,"column":1}},"key":"ikThWeCSrI"}],"key":"VBRHdENfyp"},{"type":"text","value":" - You’re here now!","position":{"start":{"line":63,"column":1},"end":{"line":63,"column":1}},"key":"fbWVKA37Jd"}],"key":"WFe4LWHCMs"}],"key":"CMJ36MpTvx"},{"type":"listItem","spread":true,"position":{"start":{"line":64,"column":1},"end":{"line":64,"column":1}},"children":[{"type":"paragraph","children":[{"type":"text","value":"🐛 ","position":{"start":{"line":64,"column":1},"end":{"line":64,"column":1}},"key":"HVTFnVguuY"},{"type":"strong","position":{"start":{"line":64,"column":1},"end":{"line":64,"column":1}},"children":[{"type":"text","value":"Issues","position":{"start":{"line":64,"column":1},"end":{"line":64,"column":1}},"key":"FDSSaqLXDg"}],"key":"K6yMjhd4Dv"},{"type":"text","value":" - ","position":{"start":{"line":64,"column":1},"end":{"line":64,"column":1}},"key":"lPnPWjexN4"},{"type":"link","url":"https://github.com/marvins/slide-forge/issues","position":{"start":{"line":64,"column":1},"end":{"line":64,"column":1}},"children":[{"type":"text","value":"GitHub Issues","position":{"start":{"line":64,"column":1},"end":{"line":64,"column":1}},"key":"CVNdlNEaGN"}],"urlSource":"https://github.com/marvins/slide-forge/issues","error":true,"key":"BQj0CYWOYf"}],"key":"wJ4OMmcg6A"}],"key":"IivPBRbh3S"},{"type":"listItem","spread":true,"position":{"start":{"line":65,"column":1},"end":{"line":65,"column":1}},"children":[{"type":"paragraph","children":[{"type":"text","value":"💬 ","position":{"start":{"line":65,"column":1},"end":{"line":65,"column":1}},"key":"RF2nRPbMaU"},{"type":"strong","position":{"start":{"line":65,"column":1},"end":{"line":65,"column":1}},"children":[{"type":"text","value":"Discussions","position":{"start":{"line":65,"column":1},"end":{"line":65,"column":1}},"key":"tg3ltlmYXj"}],"key":"m06s5X0Fto"},{"type":"text","value":" - ","position":{"start":{"line":65,"column":1},"end":{"line":65,"column":1}},"key":"pRUcEpr4px"},{"type":"link","url":"https://github.com/marvins/slide-forge/discussions","position":{"start":{"line":65,"column":1},"end":{"line":65,"column":1}},"children":[{"type":"text","value":"GitHub Discussions","position":{"start":{"line":65,"column":1},"end":{"line":65,"column":1}},"key":"sN3QkHriAz"}],"urlSource":"https://github.com/marvins/slide-forge/discussions","error":true,"key":"TY6cXeu1q1"}],"key":"xLQcLNs6vV"}],"key":"unILAwxZM8"},{"type":"listItem","spread":true,"position":{"start":{"line":66,"column":1},"end":{"line":67,"column":1}},"children":[{"type":"paragraph","children":[{"type":"text","value":"📧 ","position":{"start":{"line":66,"column":1},"end":{"line":66,"column":1}},"key":"Fy1sxSOHDW"},{"type":"strong","position":{"start":{"line":66,"column":1},"end":{"line":66,"column":1}},"children":[{"type":"text","value":"Contact","position":{"start":{"line":66,"column":1},"end":{"line":66,"column":1}},"key":"CsgEDq1rMX"}],"key":"S22CeKSpng"},{"type":"text","value":" - ","position":{"start":{"line":66,"column":1},"end":{"line":66,"column":1}},"key":"qciqH7pPfm"},{"type":"link","url":"mailto:slide-forge@example.com","position":{"start":{"line":66,"column":1},"end":{"line":66,"column":1}},"children":[{"type":"text","value":"slide​-forge@example​.com","position":{"start":{"line":66,"column":1},"end":{"line":66,"column":1}},"key":"Ann3zCWWdU"}],"urlSource":"mailto:slide-forge@example.com","key":"tYvOSaelpK"}],"key":"FTq79h2e12"}],"key":"ZgGBVBvUGt"}],"key":"CIoaVfpJlD"},{"type":"heading","depth":2,"position":{"start":{"line":68,"column":1},"end":{"line":68,"column":1}},"children":[{"type":"text","value":"Contributing","position":{"start":{"line":68,"column":1},"end":{"line":68,"column":1}},"key":"z5bEBUIxyV"}],"identifier":"contributing","label":"Contributing","html_id":"contributing","implicit":true,"key":"pX1dP1grGF"},{"type":"paragraph","position":{"start":{"line":70,"column":1},"end":{"line":70,"column":1}},"children":[{"type":"text","value":"We welcome contributions! See the ","position":{"start":{"line":70,"column":1},"end":{"line":70,"column":1}},"key":"oWdG7EPw4S"},{"type":"link","url":"/build/contributing-5426d308b97d86a34516a8301bbe8493.md","position":{"start":{"line":70,"column":1},"end":{"line":70,"column":1}},"children":[{"type":"text","value":"Contributing Guide","position":{"start":{"line":70,"column":1},"end":{"line":70,"column":1}},"key":"BACG5jIVX0"}],"urlSource":"contributing.md","static":true,"protocol":"file","key":"sLzsCgafQn"},{"type":"text","value":" for details on how to:","position":{"start":{"line":70,"column":1},"end":{"line":70,"column":1}},"key":"qZ3maa5jYH"}],"key":"W1s0iUF4r0"},{"type":"list","ordered":false,"spread":false,"position":{"start":{"line":71,"column":1},"end":{"line":75,"column":1}},"children":[{"type":"listItem","spread":true,"position":{"start":{"line":71,"column":1},"end":{"line":71,"column":1}},"children":[{"type":"paragraph","children":[{"type":"text","value":"Report bugs","position":{"start":{"line":71,"column":1},"end":{"line":71,"column":1}},"key":"tQLuYXqCpG"}],"key":"Tmqwlg4U8j"}],"key":"QcEPmnQ08B"},{"type":"listItem","spread":true,"position":{"start":{"line":72,"column":1},"end":{"line":72,"column":1}},"children":[{"type":"paragraph","children":[{"type":"text","value":"Request features","position":{"start":{"line":72,"column":1},"end":{"line":72,"column":1}},"key":"GsUKyxdMZs"}],"key":"gt3mvR1lGX"}],"key":"Bur3tgGQrv"},{"type":"listItem","spread":true,"position":{"start":{"line":73,"column":1},"end":{"line":73,"column":1}},"children":[{"type":"paragraph","children":[{"type":"text","value":"Submit pull requests","position":{"start":{"line":73,"column":1},"end":{"line":73,"column":1}},"key":"xdMSfk6OxT"}],"key":"Xmmc06Tdjo"}],"key":"juMAtGo352"},{"type":"listItem","spread":true,"position":{"start":{"line":74,"column":1},"end":{"line":75,"column":1}},"children":[{"type":"paragraph","children":[{"type":"text","value":"Improve documentation","position":{"start":{"line":74,"column":1},"end":{"line":74,"column":1}},"key":"W3WnBqmXws"}],"key":"J8hBCiJCWb"}],"key":"bXF4h3aond"}],"key":"W0aq2DniuA"},{"type":"thematicBreak","position":{"start":{"line":76,"column":1},"end":{"line":76,"column":1}},"key":"vrx44tpu5H"},{"type":"paragraph","position":{"start":{"line":78,"column":1},"end":{"line":78,"column":1}},"children":[{"type":"text","value":"Let’s get started transforming your LaTeX presentations into PowerPoint slides!","position":{"start":{"line":78,"column":1},"end":{"line":78,"column":1}},"key":"d7Hhley1B3"}],"key":"uRpjvW2k6A"}],"key":"sNDN1MwTOX"}],"key":"s1gRAQNqtz"},"references":{"cite":{"order":[],"data":{}}},"footer":{"navigation":{"next":{"title":"Installation","url":"/installation","group":"Getting Started"}}},"domain":"http://localhost:3000"}